<?xml version="1.0" ?>
  <Gesture Name="X05" Subject="1" Speed="medium" Number="5" NumPts="155" AppName="dollarstore-notepad" Date="2022-04-20" Time="1650477172">
    <Stroke>
      <Point X="161.0" Y="247.0" T="1650477172"/>
      <Point X="163.0" Y="247.0" T="1650477172"/>
      <Point X="163.49362255025417" Y="246.75318872487293" T="1650477172"/>
      <Point X="165.0" Y="246.0" T="1650477172"/>
      <Point X="165.82317781043534" Y="246.27439260347845" T="1650477172"/>
      <Point X="168.24411018548335" Y="247.08137006182778" T="1650477172"/>
      <Point X="170.66504256053136" Y="247.88834752017712" T="1650477172"/>
      <Point X="173.08597493557937" Y="248.69532497852646" T="1650477172"/>
      <Point X="174.0" Y="249.0" T="1650477172"/>
      <Point X="175.4207258372856" Y="249.7103629186428" T="1650477172"/>
      <Point X="177.7032027695396" Y="250.8516013847698" T="1650477172"/>
      <Point X="179.98567970179357" Y="251.9928398508968" T="1650477172"/>
      <Point X="182.26815663404756" Y="253.13407831702378" T="1650477172"/>
      <Point X="184.55063356630154" Y="254.27531678315077" T="1650477172"/>
      <Point X="186.83311049855553" Y="255.41655524927776" T="1650477172"/>
      <Point X="189.1155874308095" Y="256.5577937154048" T="1650477172"/>
      <Point X="191.3980643630635" Y="257.6990321815318" T="1650477172"/>
      <Point X="193.68054129531748" Y="258.84027064765877" T="1650477172"/>
      <Point X="195.96301822757147" Y="259.98150911378576" T="1650477172"/>
      <Point X="198.24549515982548" Y="261.12274757991275" T="1650477172"/>
      <Point X="200.0" Y="262.0" T="1650477172"/>
      <Point X="200.49653986811413" Y="262.3192042009305" T="1650477172"/>
      <Point X="202.64313210644843" Y="263.69915635414543" T="1650477172"/>
      <Point X="204.78972434478274" Y="265.07910850736033" T="1650477172"/>
      <Point X="206.93631658311705" Y="266.45906066057523" T="1650477172"/>
      <Point X="209.08290882145135" Y="267.83901281379013" T="1650477172"/>
      <Point X="211.22950105978566" Y="269.21896496700504" T="1650477172"/>
      <Point X="213.37609329811994" Y="270.59891712021994" T="1650477172"/>
      <Point X="214.0" Y="271.0" T="1650477172"/>
      <Point X="215.47715224668562" Y="272.04631617473564" T="1650477172"/>
      <Point X="217.55955433934432" Y="273.5213509903689" T="1650477172"/>
      <Point X="219.641956432003" Y="274.99638580600214" T="1650477172"/>
      <Point X="221.7243585246617" Y="276.4714206216354" T="1650477172"/>
      <Point X="223.8067606173204" Y="277.94645543726864" T="1650477172"/>
      <Point X="225.8891627099791" Y="279.4214902529019" T="1650477172"/>
      <Point X="227.9715648026378" Y="280.89652506853514" T="1650477172"/>
      <Point X="230.0539668952965" Y="282.3715598841684" T="1650477172"/>
      <Point X="232.1363689879552" Y="283.84659469980164" T="1650477172"/>
      <Point X="234.2187710806139" Y="285.3216295154349" T="1650477172"/>
      <Point X="236.3011731732726" Y="286.79666433106814" T="1650477172"/>
      <Point X="238.38357526593128" Y="288.2716991467014" T="1650477172"/>
      <Point X="240.46597735858998" Y="289.74673396233464" T="1650477172"/>
      <Point X="242.54837945124868" Y="291.2217687779679" T="1650477172"/>
      <Point X="244.63078154390737" Y="292.69680359360115" T="1650477172"/>
      <Point X="246.71318363656607" Y="294.1718384092344" T="1650477172"/>
      <Point X="248.79558572922477" Y="295.64687322486765" T="1650477172"/>
      <Point X="250.87798782188347" Y="297.1219080405009" T="1650477172"/>
      <Point X="252.96038991454216" Y="298.59694285613415" T="1650477172"/>
      <Point X="255.04279200720086" Y="300.0719776717674" T="1650477172"/>
      <Point X="257.1251940998596" Y="301.5470124874006" T="1650477172"/>
      <Point X="259.2075961925183" Y="303.02204730303384" T="1650477172"/>
      <Point X="261.289998285177" Y="304.49708211866704" T="1650477172"/>
      <Point X="262.0" Y="305.0" T="1650477172"/>
      <Point X="263.33596113273813" Y="306.02161733679975" T="1650477172"/>
      <Point X="265.3630723922905" Y="307.5717612411633" T="1650477172"/>
      <Point X="267.3901836518429" Y="309.12190514552685" T="1650477172"/>
      <Point X="269.4172949113953" Y="310.67204904989046" T="1650477172"/>
      <Point X="271.4444061709477" Y="312.222192954254" T="1650477172"/>
      <Point X="273.4715174305" Y="313.7723368586176" T="1650477172"/>
      <Point X="275.4986286900524" Y="315.3224807629812" T="1650477172"/>
      <Point X="277.5257399496047" Y="316.8726246673448" T="1650477172"/>
      <Point X="279.0" Y="318.0" T="1650477172"/>
      <Point X="279.5567780022613" Y="318.41758350169596" T="1650477172"/>
      <Point X="281.59828743329933" Y="319.94871557497447" T="1650477172"/>
      <Point X="283.63979686433737" Y="321.479847648253" T="1650477172"/>
      <Point X="285.6813062953754" Y="323.0109797215315" T="1650477172"/>
      <Point X="287.72281572641344" Y="324.54211179481007" T="1650477172"/>
      <Point X="289.7643251574515" Y="326.0732438680886" T="1650477172"/>
      <Point X="291.0" Y="327.0" T="1650477172"/>
      <Point X="291.7122638775445" Y="327.7122638775445" T="1650477172"/>
      <Point X="293.5167203307236" Y="329.5167203307236" T="1650477172"/>
      <Point X="295.32117678390273" Y="331.32117678390273" T="1650477172"/>
      <Point X="296.0" Y="332.0" T="1650477172"/>
      <Point X="297.5101954615089" Y="332.50339848716965" T="1650477172"/>
      <Point X="299.0" Y="333.0" T="1650477172"/>
    </Stroke>
    <Stroke>
      <Point X="265.0" Y="217.0" T="1650477172"/>
      <Point X="265.0" Y="218.0" T="1650477172"/>
      <Point X="265.0" Y="219.8043084931952" T="1650477172"/>
      <Point X="265.0" Y="222.60861698639042" T="1650477172"/>
      <Point X="265.0" Y="225.0" T="1650477172"/>
      <Point X="264.9261336446404" Y="225.40626495447788" T="1650477172"/>
      <Point X="264.42448369098724" Y="228.16533969957027" T="1650477172"/>
      <Point X="263.9228337373341" Y="230.92441444466266" T="1650477172"/>
      <Point X="263.42118378368093" Y="233.68348918975505" T="1650477172"/>
      <Point X="263.0" Y="236.0" T="1650477172"/>
      <Point X="262.79883457506935" Y="236.4023308498613" T="1650477172"/>
      <Point X="261.54470969093643" Y="238.9105806181271" T="1650477172"/>
      <Point X="260.2905848068035" Y="241.41883038639293" T="1650477172"/>
      <Point X="259.0364599226706" Y="243.92708015465874" T="1650477172"/>
      <Point X="257.78233503853767" Y="246.43532992292455" T="1650477172"/>
      <Point X="256.5282101544048" Y="248.94357969119037" T="1650477172"/>
      <Point X="255.2740852702719" Y="251.45182945945618" T="1650477172"/>
      <Point X="255.0" Y="252.0" T="1650477172"/>
      <Point X="254.01996038613902" Y="253.960079227722" T="1650477172"/>
      <Point X="252.76583550200613" Y="256.4683289959878" T="1650477172"/>
      <Point X="251.51171061787323" Y="258.9765787642536" T="1650477172"/>
      <Point X="250.2575857337403" Y="261.4848285325194" T="1650477172"/>
      <Point X="249.00346084960742" Y="263.99307830078516" T="1650477172"/>
      <Point X="247.74933596547453" Y="266.50132806905094" T="1650477172"/>
      <Point X="246.49521108134164" Y="269.0095778373167" T="1650477172"/>
      <Point X="245.24108619720874" Y="271.5178276055825" T="1650477172"/>
      <Point X="245.0" Y="272.0" T="1650477172"/>
      <Point X="244.03028880846122" Y="274.0471680710263" T="1650477172"/>
      <Point X="242.82980263608863" Y="276.58152776825733" T="1650477172"/>
      <Point X="241.62931646371604" Y="279.11588746548836" T="1650477172"/>
      <Point X="240.42883029134344" Y="281.6502471627194" T="1650477172"/>
      <Point X="239.22834411897085" Y="284.1846068599504" T="1650477172"/>
      <Point X="238.02785794659826" Y="286.71896655718143" T="1650477172"/>
      <Point X="236.82737177422567" Y="289.25332625441246" T="1650477172"/>
      <Point X="236.0" Y="291.0" T="1650477172"/>
      <Point X="235.5515723019558" Y="291.74737949674034" T="1650477172"/>
      <Point X="234.10876748529748" Y="294.15205419117086" T="1650477172"/>
      <Point X="232.66596266863917" Y="296.5567288856014" T="1650477172"/>
      <Point X="231.22315785198086" Y="298.9614035800319" T="1650477172"/>
      <Point X="230.0" Y="301.0" T="1650477172"/>
      <Point X="229.79556990330093" Y="301.37478851061496" T="1650477172"/>
      <Point X="228.45272080624878" Y="303.8366785218773" T="1650477172"/>
      <Point X="227.10987170919663" Y="306.2985685331396" T="1650477172"/>
      <Point X="225.76702261214444" Y="308.76045854440184" T="1650477172"/>
      <Point X="224.4241735150923" Y="311.22234855566415" T="1650477172"/>
      <Point X="224.0" Y="312.0" T="1650477172"/>
      <Point X="223.24426766076385" Y="313.7633754582177" T="1650477172"/>
      <Point X="222.1395964261248" Y="316.3409416723755" T="1650477172"/>
      <Point X="221.03492519148574" Y="318.9185078865333" T="1650477172"/>
      <Point X="221.0" Y="319.0" T="1650477172"/>
      <Point X="219.9555201095447" Y="321.50675173709277" T="1650477172"/>
      <Point X="218.8769399198542" Y="324.0953441923499" T="1650477172"/>
      <Point X="217.79835973016375" Y="326.683936647607" T="1650477172"/>
      <Point X="216.71977954047327" Y="329.27252910286415" T="1650477172"/>
      <Point X="216.0" Y="331.0" T="1650477172"/>
      <Point X="215.6651149905503" Y="331.87070102456914" T="1650477172"/>
      <Point X="214.65842690956504" Y="334.4880900351308" T="1650477172"/>
      <Point X="213.6517388285798" Y="337.1054790456925" T="1650477172"/>
      <Point X="212.64505074759452" Y="339.7228680562542" T="1650477172"/>
      <Point X="211.63836266660928" Y="342.34025706681587" T="1650477172"/>
      <Point X="211.0" Y="344.0" T="1650477172"/>
      <Point X="210.78501563773798" Y="345.0032603572227" T="1650477172"/>
      <Point X="210.19743143463853" Y="347.74531997168674" T="1650477172"/>
      <Point X="209.6098472315391" Y="350.48737958615084" T="1650477172"/>
      <Point X="209.02226302843965" Y="353.2294392006149" T="1650477172"/>
      <Point X="208.43467882534023" Y="355.971498815079" T="1650477172"/>
      <Point X="208.0" Y="358.0" T="1650477172"/>
      <Point X="207.81196880510956" Y="358.70511698083914" T="1650477172"/>
      <Point X="207.08940324576403" Y="361.4147378283849" T="1650477172"/>
      <Point X="206.3668376864185" Y="364.12435867593064" T="1650477172"/>
      <Point X="205.64427212707298" Y="366.8339795234764" T="1650477172"/>
      <Point X="204.92170656772745" Y="369.54360037102214" T="1650477172"/>
      <Point X="204.1991410083819" Y="372.2532212185679" T="1650477172"/>
      <Point X="204.0" Y="373.0" T="1650477172"/>
      <Point X="203.71271191333238" Y="375.01101660667325" T="1650477172"/>
      <Point X="203.3161228029169" Y="377.78714037958156" T="1650477172"/>
      <Point X="203.0" Y="380.0" T="1650477172"/>
      <Point X="202.8884133086026" Y="380.5579334569871" T="1650477172"/>
      <Point X="202.33844316518196" Y="383.3077841740902" T="1650477172"/>
      <Point X="202.0" Y="385.0" T="1650477172"/>
    </Stroke>
  </Gesture>
