<?xml version="1.0" ?>
  <Gesture Name="arrowhead06" Subject="1" Speed="medium" Number="6" NumPts="160" AppName="dollarstore-notepad" Date="2022-04-20" Time="1650477172">
    <Stroke>
      <Point X="176.0" Y="331.0" T="1650477172"/>
      <Point X="178.8442671179061" Y="327.80019949235566" T="1650477172"/>
      <Point X="181.68853423581217" Y="324.6003989847113" T="1650477172"/>
      <Point X="184.0" Y="322.0" T="1650477172"/>
      <Point X="184.48118334193802" Y="321.3584222107493" T="1650477172"/>
      <Point X="187.04989670500916" Y="317.9334710599878" T="1650477172"/>
      <Point X="189.6186100680803" Y="314.5085199092263" T="1650477172"/>
      <Point X="192.1873234311514" Y="311.08356875846476" T="1650477172"/>
      <Point X="193.0" Y="310.0" T="1650477172"/>
      <Point X="194.87364560149683" Y="307.7516252782038" T="1650477172"/>
      <Point X="197.61439597190986" Y="304.46272483370814" T="1650477172"/>
      <Point X="200.35514634232288" Y="301.1738243892125" T="1650477172"/>
      <Point X="203.09589671273594" Y="297.88492394471683" T="1650477172"/>
      <Point X="205.836647083149" Y="294.5960235002212" T="1650477172"/>
      <Point X="208.57739745356204" Y="291.3071230557255" T="1650477172"/>
      <Point X="211.31814782397507" Y="288.0182226112299" T="1650477172"/>
      <Point X="214.05889819438812" Y="284.7293221667342" T="1650477172"/>
      <Point X="216.79964856480117" Y="281.44042172223857" T="1650477172"/>
      <Point X="219.54039893521423" Y="278.1515212777429" T="1650477172"/>
      <Point X="222.28114930562725" Y="274.86262083324726" T="1650477172"/>
      <Point X="225.0218996760403" Y="271.5737203887516" T="1650477172"/>
      <Point X="227.76265004645336" Y="268.28481994425596" T="1650477172"/>
      <Point X="230.5034004168664" Y="264.9959194997603" T="1650477172"/>
      <Point X="233.0" Y="262.0" T="1650477172"/>
      <Point X="233.23526368935887" Y="261.69983598254214" T="1650477172"/>
      <Point X="235.87625064229883" Y="258.33030090465326" T="1650477172"/>
      <Point X="238.51723759523878" Y="254.96076582676434" T="1650477172"/>
      <Point X="241.15822454817874" Y="251.59123074887543" T="1650477172"/>
      <Point X="243.7992115011187" Y="248.22169567098652" T="1650477172"/>
      <Point X="246.44019845405865" Y="244.8521605930976" T="1650477172"/>
      <Point X="249.0811854069986" Y="241.4826255152087" T="1650477172"/>
      <Point X="251.72217235993855" Y="238.11309043731978" T="1650477172"/>
      <Point X="254.3631593128785" Y="234.74355535943087" T="1650477172"/>
      <Point X="257.00414626581846" Y="231.37402028154196" T="1650477172"/>
      <Point X="259.6451332187584" Y="228.00448520365305" T="1650477172"/>
      <Point X="262.0" Y="225.0" T="1650477172"/>
      <Point X="262.3011948073853" Y="224.64728502819352" T="1650477172"/>
      <Point X="265.08132579876616" Y="221.39160531460277" T="1650477172"/>
      <Point X="267.86145679014703" Y="218.13592560101202" T="1650477172"/>
      <Point X="270.6415877815279" Y="214.88024588742127" T="1650477172"/>
      <Point X="273.4217187729088" Y="211.62456617383052" T="1650477172"/>
      <Point X="276.20184976428965" Y="208.36888646023976" T="1650477172"/>
      <Point X="278.9819807556705" Y="205.113206746649" T="1650477172"/>
      <Point X="281.7621117470514" Y="201.85752703305826" T="1650477172"/>
      <Point X="284.54224273843226" Y="198.6018473194675" T="1650477172"/>
      <Point X="287.32237372981314" Y="195.34616760587676" T="1650477172"/>
      <Point X="290.102504721194" Y="192.090487892286" T="1650477172"/>
      <Point X="292.8826357125749" Y="188.83480817869525" T="1650477172"/>
      <Point X="295.66276670395575" Y="185.5791284651045" T="1650477172"/>
      <Point X="298.4428976953366" Y="182.32344875151375" T="1650477172"/>
      <Point X="301.2230286867175" Y="179.06776903792297" T="1650477172"/>
      <Point X="304.00315967809837" Y="175.81208932433222" T="1650477172"/>
      <Point X="306.78329066947924" Y="172.55640961074147" T="1650477172"/>
      <Point X="309.5634216608601" Y="169.3007298971507" T="1650477172"/>
      <Point X="312.343552652241" Y="166.04505018355994" T="1650477172"/>
      <Point X="315.12368364362186" Y="162.78937046996919" T="1650477172"/>
      <Point X="317.90381463500273" Y="159.5336907563784" T="1650477172"/>
      <Point X="320.6839456263836" Y="156.27801104278763" T="1650477172"/>
      <Point X="323.4640766177645" Y="153.02233132919687" T="1650477172"/>
      <Point X="326.24420760914535" Y="149.76665161560612" T="1650477172"/>
      <Point X="329.0243386005262" Y="146.51097190201534" T="1650477172"/>
      <Point X="331.8044695919071" Y="143.2552921884246" T="1650477172"/>
      <Point X="334.58460058328797" Y="139.99961247483384" T="1650477172"/>
      <Point X="337.36473157466884" Y="136.74393276124306" T="1650477172"/>
      <Point X="338.0" Y="136.0" T="1650477172"/>
      <Point X="339.9817545117277" Y="133.3576606510298" T="1650477172"/>
      <Point X="342.5504678747988" Y="129.93270950026826" T="1650477172"/>
      <Point X="344.0" Y="128.0" T="1650477172"/>
      <Point X="344.92544898530946" Y="126.38046427570843" T="1650477172"/>
      <Point X="347.049513520138" Y="122.66335133975849" T="1650477172"/>
      <Point X="348.0" Y="121.0" T="1650477172"/>
      <Point X="349.4192533150331" Y="119.10766224662255" T="1650477172"/>
      <Point X="351.0" Y="117.0" T="1650477172"/>
    </Stroke>
    <Stroke>
      <Point X="278.0" Y="129.0" T="1650477172"/>
      <Point X="279.0" Y="129.0" T="1650477172"/>
      <Point X="280.30851769331576" Y="129.0" T="1650477172"/>
      <Point X="281.0" Y="129.0" T="1650477172"/>
      <Point X="282.6170353866315" Y="129.0" T="1650477172"/>
      <Point X="284.9255530799473" Y="129.0" T="1650477172"/>
      <Point X="286.0" Y="129.0" T="1650477172"/>
      <Point X="287.23407077326306" Y="129.0" T="1650477172"/>
      <Point X="289.5425884665788" Y="129.0" T="1650477172"/>
      <Point X="291.8511061598946" Y="129.0" T="1650477172"/>
      <Point X="293.0" Y="129.0" T="1650477172"/>
      <Point X="294.15962385321035" Y="129.0" T="1650477172"/>
      <Point X="296.4681415465261" Y="129.0" T="1650477172"/>
      <Point X="298.7766592398419" Y="129.0" T="1650477172"/>
      <Point X="301.08517693315764" Y="129.0" T="1650477172"/>
      <Point X="303.3936946264734" Y="129.0" T="1650477172"/>
      <Point X="305.70221231978917" Y="129.0" T="1650477172"/>
      <Point X="308.01073001310493" Y="129.0" T="1650477172"/>
      <Point X="309.0" Y="129.0" T="1650477172"/>
      <Point X="310.3192477064207" Y="129.0" T="1650477172"/>
      <Point X="312.0" Y="129.0" T="1650477172"/>
      <Point X="312.62776539973646" Y="129.0" T="1650477172"/>
      <Point X="314.9362830930522" Y="129.0" T="1650477172"/>
      <Point X="317.244800786368" Y="129.0" T="1650477172"/>
      <Point X="319.55331847968375" Y="129.0" T="1650477172"/>
      <Point X="321.8618361729995" Y="129.0" T="1650477172"/>
      <Point X="322.0" Y="129.0" T="1650477172"/>
      <Point X="324.1703538663153" Y="129.0" T="1650477172"/>
      <Point X="326.47887155963105" Y="129.0" T="1650477172"/>
      <Point X="327.0" Y="129.0" T="1650477172"/>
      <Point X="328.7873892529468" Y="129.0" T="1650477172"/>
      <Point X="331.0959069462626" Y="129.0" T="1650477172"/>
      <Point X="332.0" Y="129.0" T="1650477172"/>
      <Point X="333.40442463957834" Y="129.0" T="1650477172"/>
      <Point X="334.0" Y="129.0" T="1650477172"/>
      <Point X="334.0" Y="130.0" T="1650477172"/>
      <Point X="334.0" Y="130.7129423328941" T="1650477172"/>
      <Point X="334.0" Y="131.0" T="1650477172"/>
      <Point X="334.0" Y="133.02146002620987" T="1650477172"/>
      <Point X="334.0" Y="134.0" T="1650477172"/>
      <Point X="334.73773890199607" Y="135.10660835299407" T="1650477172"/>
      <Point X="336.0" Y="137.0" T="1650477172"/>
      <Point X="336.01976648242646" Y="137.02635530990193" T="1650477172"/>
      <Point X="337.4048770984159" Y="138.87316946455454" T="1650477172"/>
      <Point X="338.78998771440536" Y="140.71998361920714" T="1650477172"/>
      <Point X="339.0" Y="141.0" T="1650477172"/>
      <Point X="339.8104319149346" Y="142.78295021285618" T="1650477172"/>
      <Point X="340.76570333340004" Y="144.88454733348016" T="1650477172"/>
      <Point X="341.72097475186547" Y="146.98614445410414" T="1650477172"/>
      <Point X="342.6762461703309" Y="149.08774157472808" T="1650477172"/>
      <Point X="343.6315175887964" Y="151.18933869535203" T="1650477172"/>
      <Point X="344.0" Y="152.0" T="1650477172"/>
      <Point X="344.2613284608558" Y="153.393751791231" T="1650477172"/>
      <Point X="344.6867618046944" Y="155.66272962503686" T="1650477172"/>
      <Point X="345.11219514853303" Y="157.9317074588427" T="1650477172"/>
      <Point X="345.5376284923716" Y="160.20068529264856" T="1650477172"/>
      <Point X="345.9630618362102" Y="162.4696631264544" T="1650477172"/>
      <Point X="346.3884951800488" Y="164.73864096026026" T="1650477172"/>
      <Point X="346.8139285238874" Y="167.0076187940661" T="1650477172"/>
      <Point X="347.0" Y="168.0" T="1650477172"/>
      <Point X="347.1175917170474" Y="169.2935088875215" T="1650477172"/>
      <Point X="347.3265950886641" Y="171.59254597530517" T="1650477172"/>
      <Point X="347.53559846028077" Y="173.89158306308883" T="1650477172"/>
      <Point X="347.74460183189746" Y="176.1906201508725" T="1650477172"/>
      <Point X="347.95360520351414" Y="178.48965723865615" T="1650477172"/>
      <Point X="348.16260857513083" Y="180.7886943264398" T="1650477172"/>
      <Point X="348.3716119467475" Y="183.08773141422347" T="1650477172"/>
      <Point X="348.5806153183642" Y="185.38676850200713" T="1650477172"/>
      <Point X="348.7896186899809" Y="187.6858055897908" T="1650477172"/>
      <Point X="348.9986220615976" Y="189.98484267757445" T="1650477172"/>
      <Point X="349.2076254332143" Y="192.2838797653581" T="1650477172"/>
      <Point X="349.416628804831" Y="194.58291685314177" T="1650477172"/>
      <Point X="349.6256321764477" Y="196.88195394092543" T="1650477172"/>
      <Point X="349.83463554806445" Y="199.1809910287091" T="1650477172"/>
      <Point X="350.0" Y="201.0" T="1650477172"/>
      <Point X="350.0597856874993" Y="201.47828549999426" T="1650477172"/>
      <Point X="350.3461220668842" Y="203.76897653507356" T="1650477172"/>
      <Point X="350.63245844626914" Y="206.05966757015287" T="1650477172"/>
      <Point X="350.918794825654" Y="208.35035860523217" T="1650477172"/>
      <Point X="351.0" Y="209.0" T="1650477172"/>
      <Point X="351.0" Y="210.65382064724295" T="1650477172"/>
      <Point X="351.0" Y="212.96233834055872" T="1650477172"/>
      <Point X="351.0" Y="215.0" T="1650477172"/>
      <Point X="351.0" Y="215.27085603387448" T="1650477172"/>
      <Point X="351.0" Y="217.0" T="1650477172"/>
      <Point X="351.0" Y="216.42062627280976" T="1650477172"/>
      <Point X="351.0" Y="215.0" T="1650477172"/>
    </Stroke>
  </Gesture>
