<?xml version="1.0" ?>
  <Gesture Name="six-point star06" Subject="1" Speed="medium" Number="6" NumPts="246" AppName="dollarstore-notepad" Date="2022-04-20" Time="1650477172">
    <Stroke>
      <Point X="179.0" Y="275.0" T="1650477172"/>
      <Point X="180.0" Y="274.0" T="1650477172"/>
      <Point X="182.8440068640394" Y="269.73398970394095" T="1650477172"/>
      <Point X="184.0" Y="268.0" T="1650477172"/>
      <Point X="186.67439415250638" Y="264.43414112999153" T="1650477172"/>
      <Point X="190.0" Y="260.0" T="1650477172"/>
      <Point X="190.47820253803647" Y="259.12329534693316" T="1650477172"/>
      <Point X="193.61052748586644" Y="253.38069960924489" T="1650477172"/>
      <Point X="196.0" Y="249.0" T="1650477172"/>
      <Point X="196.7981470678696" Y="247.66975488688402" T="1650477172"/>
      <Point X="200.16362836579722" Y="242.06061939033796" T="1650477172"/>
      <Point X="203.52910966372485" Y="236.4514838937919" T="1650477172"/>
      <Point X="206.89459096165248" Y="230.84234839724584" T="1650477172"/>
      <Point X="210.2600722595801" Y="225.23321290069978" T="1650477172"/>
      <Point X="213.62555355750774" Y="219.62407740415375" T="1650477172"/>
      <Point X="214.0" Y="219.0" T="1650477172"/>
      <Point X="216.99103485543537" Y="214.0149419076077" T="1650477172"/>
      <Point X="220.356516153363" Y="208.40580641106163" T="1650477172"/>
      <Point X="223.72199745129063" Y="202.7966709145156" T="1650477172"/>
      <Point X="226.0" Y="199.0" T="1650477172"/>
      <Point X="227.10777359563707" Y="197.19986790708975" T="1650477172"/>
      <Point X="230.5360624896818" Y="191.6288984542671" T="1650477172"/>
      <Point X="233.9643513837265" Y="186.05792900144445" T="1650477172"/>
      <Point X="234.0" Y="186.0" T="1650477172"/>
      <Point X="237.3304857782753" Y="180.4491903695412" T="1650477172"/>
      <Point X="240.0" Y="176.0" T="1650477172"/>
      <Point X="240.75035230060402" Y="174.87447154909395" T="1650477172"/>
      <Point X="244.37882370519614" Y="169.4317644422058" T="1650477172"/>
      <Point X="246.0" Y="167.0" T="1650477172"/>
      <Point X="248.5588092335874" Y="164.4411907664126" T="1650477172"/>
      <Point X="249.0" Y="164.0" T="1650477172"/>
      <Point X="250.0" Y="162.0" T="1650477172"/>
      <Point X="250.0" Y="161.0" T="1650477172"/>
      <Point X="251.0" Y="160.0" T="1650477172"/>
      <Point X="252.0" Y="160.0" T="1650477172"/>
      <Point X="252.0" Y="160.26710034507846" T="1650477172"/>
      <Point X="252.0" Y="161.0" T="1650477172"/>
      <Point X="252.0" Y="163.0" T="1650477172"/>
      <Point X="252.9236775725128" Y="166.69471029005112" T="1650477172"/>
      <Point X="253.0" Y="167.0" T="1650477172"/>
      <Point X="254.51018067099352" Y="173.04072268397414" T="1650477172"/>
      <Point X="255.0" Y="175.0" T="1650477172"/>
      <Point X="257.02218495365196" Y="179.0443699073039" T="1650477172"/>
      <Point X="259.9475521232672" Y="184.89510424653437" T="1650477172"/>
      <Point X="260.0" Y="185.0" T="1650477172"/>
      <Point X="263.18721779100224" Y="190.57763113425398" T="1650477172"/>
      <Point X="264.0" Y="192.0" T="1650477172"/>
      <Point X="266.3478622450096" Y="196.30441411585093" T="1650477172"/>
      <Point X="269.48018719283954" Y="202.0470098535392" T="1650477172"/>
      <Point X="270.0" Y="203.0" T="1650477172"/>
      <Point X="272.5865845930515" Y="207.80365710138136" T="1650477172"/>
      <Point X="275.6878231765444" Y="213.56310018501097" T="1650477172"/>
      <Point X="277.0" Y="216.0" T="1650477172"/>
      <Point X="278.68760396735826" Y="219.37520793471646" T="1650477172"/>
      <Point X="281.6129711369735" Y="225.22594227394694" T="1650477172"/>
      <Point X="284.53833830658874" Y="231.07667661317743" T="1650477172"/>
      <Point X="285.0" Y="232.0" T="1650477172"/>
      <Point X="287.83436376462" Y="236.72393960769995" T="1650477172"/>
      <Point X="288.0" Y="237.0" T="1650477172"/>
      <Point X="290.183770418043" Y="242.8233877814481" T="1650477172"/>
      <Point X="292.480581156448" Y="248.94821641719466" T="1650477172"/>
      <Point X="294.0" Y="253.0" T="1650477172"/>
      <Point X="294.89919587900397" Y="255.02319072775887" T="1650477172"/>
      <Point X="297.55587748901274" Y="261.0007243502787" T="1650477172"/>
      <Point X="298.0" Y="262.0" T="1650477172"/>
      <Point X="300.0" Y="267.0" T="1650477172"/>
      <Point X="300.02326026452" Y="267.0581506613" T="1650477172"/>
      <Point X="302.0" Y="272.0" T="1650477172"/>
      <Point X="302.385413728077" Y="273.1562411842311" T="1650477172"/>
      <Point X="303.0" Y="275.0" T="1650477172"/>
      <Point X="303.0" Y="277.0" T="1650477172"/>
      <Point X="304.0" Y="279.0" T="1650477172"/>
      <Point X="303.6382405650421" Y="279.0" T="1650477172"/>
      <Point X="303.0" Y="279.0" T="1650477172"/>
      <Point X="300.0" Y="278.0" T="1650477172"/>
      <Point X="298.0" Y="277.0" T="1650477172"/>
      <Point X="297.49526635230444" Y="277.0" T="1650477172"/>
      <Point X="296.0" Y="277.0" T="1650477172"/>
      <Point X="295.0" Y="276.0" T="1650477172"/>
      <Point X="291.3726913697614" Y="275.81863456848805" T="1650477172"/>
      <Point X="284.8395328698205" Y="275.491976643491" T="1650477172"/>
      <Point X="278.3063743698796" Y="275.16531871849395" T="1650477172"/>
      <Point X="275.0" Y="275.0" T="1650477172"/>
      <Point X="271.769184907555" Y="275.0" T="1650477172"/>
      <Point X="265.22786505714913" Y="275.0" T="1650477172"/>
      <Point X="260.0" Y="275.0" T="1650477172"/>
      <Point X="258.6865452067433" Y="275.0" T="1650477172"/>
      <Point X="252.14522535633745" Y="275.0" T="1650477172"/>
      <Point X="245.6039055059316" Y="275.0" T="1650477172"/>
      <Point X="239.06258565552577" Y="275.0" T="1650477172"/>
      <Point X="237.0" Y="275.0" T="1650477172"/>
      <Point X="232.52126580511992" Y="275.0" T="1650477172"/>
      <Point X="225.97994595471408" Y="275.0" T="1650477172"/>
      <Point X="220.0" Y="275.0" T="1650477172"/>
      <Point X="219.43862610430824" Y="275.0" T="1650477172"/>
      <Point X="212.8973062539024" Y="275.0" T="1650477172"/>
      <Point X="206.35598640349656" Y="275.0" T="1650477172"/>
      <Point X="202.0" Y="275.0" T="1650477172"/>
      <Point X="199.81466655309072" Y="275.0" T="1650477172"/>
      <Point X="193.27334670268488" Y="275.0" T="1650477172"/>
      <Point X="190.0" Y="275.0" T="1650477172"/>
      <Point X="186.73202685227903" Y="275.0" T="1650477172"/>
      <Point X="180.1907070018732" Y="275.0" T="1650477172"/>
      <Point X="180.0" Y="275.0" T="1650477172"/>
      <Point X="175.0" Y="275.0" T="1650477172"/>
      <Point X="173.64938715146735" Y="275.0" T="1650477172"/>
      <Point X="167.1080673010615" Y="275.0" T="1650477172"/>
      <Point X="163.0" Y="275.0" T="1650477172"/>
      <Point X="160.56674745065567" Y="275.0" T="1650477172"/>
      <Point X="160.0" Y="275.0" T="1650477172"/>
      <Point X="155.0" Y="275.0" T="1650477172"/>
      <Point X="154.02542760024983" Y="275.0" T="1650477172"/>
      <Point X="150.0" Y="275.0" T="1650477172"/>
    </Stroke>
    <Stroke>
      <Point X="166.0" Y="192.0" T="1650477172"/>
      <Point X="168.0" Y="192.0" T="1650477172"/>
      <Point X="171.33834085555017" Y="195.81524669205734" T="1650477172"/>
      <Point X="175.0" Y="200.0" T="1650477172"/>
      <Point X="175.8770950309665" Y="201.2279330433531" T="1650477172"/>
      <Point X="179.9862041157511" Y="206.98068576205154" T="1650477172"/>
      <Point X="180.0" Y="207.0" T="1650477172"/>
      <Point X="183.9083306301767" Y="212.86249594526504" T="1650477172"/>
      <Point X="186.0" Y="216.0" T="1650477172"/>
      <Point X="187.91736995318348" Y="218.68431793445686" T="1650477172"/>
      <Point X="191.0" Y="223.0" T="1650477172"/>
      <Point X="191.97961236879274" Y="224.46941855318912" T="1650477172"/>
      <Point X="195.90110899491165" Y="230.3516634923675" T="1650477172"/>
      <Point X="197.0" Y="232.0" T="1650477172"/>
      <Point X="200.31156794487444" Y="235.86349593568684" T="1650477172"/>
      <Point X="203.0" Y="239.0" T="1650477172"/>
      <Point X="204.45793342955923" Y="241.55138350172865" T="1650477172"/>
      <Point X="207.0" Y="246.0" T="1650477172"/>
      <Point X="208.13101954678103" Y="247.58342736549343" T="1650477172"/>
      <Point X="212.0" Y="253.0" T="1650477172"/>
      <Point X="212.24012863156563" Y="253.33618008419188" T="1650477172"/>
      <Point X="216.34923771635022" Y="259.0889328028903" T="1650477172"/>
      <Point X="217.0" Y="260.0" T="1650477172"/>
      <Point X="220.71691355237868" Y="264.64614194047334" T="1650477172"/>
      <Point X="221.0" Y="265.0" T="1650477172"/>
      <Point X="224.0" Y="270.0" T="1650477172"/>
      <Point X="224.43569884472427" Y="270.6535482670864" T="1650477172"/>
      <Point X="226.0" Y="273.0" T="1650477172"/>
      <Point X="228.0" Y="275.0" T="1650477172"/>
      <Point X="228.0" Y="276.0" T="1650477172"/>
      <Point X="228.29773964460895" Y="276.29773964460895" T="1650477172"/>
      <Point X="229.0" Y="277.0" T="1650477172"/>
      <Point X="230.0" Y="280.0" T="1650477172"/>
      <Point X="231.0" Y="282.0" T="1650477172"/>
      <Point X="231.2518351243542" Y="282.6295878108855" T="1650477172"/>
      <Point X="233.0" Y="287.0" T="1650477172"/>
      <Point X="234.05654238694422" Y="289.11308477388843" T="1650477172"/>
      <Point X="235.0" Y="291.0" T="1650477172"/>
      <Point X="237.0" Y="294.0" T="1650477172"/>
      <Point X="237.0" Y="295.0" T="1650477172"/>
      <Point X="237.25059295024317" Y="295.2505929502432" T="1650477172"/>
      <Point X="239.0" Y="297.0" T="1650477172"/>
      <Point X="241.0" Y="299.0" T="1650477172"/>
      <Point X="241.90917382560858" Y="300.5152897093476" T="1650477172"/>
      <Point X="244.0" Y="304.0" T="1650477172"/>
      <Point X="246.12538123415982" Y="306.1253812341598" T="1650477172"/>
      <Point X="247.0" Y="307.0" T="1650477172"/>
      <Point X="249.0" Y="309.0" T="1650477172"/>
      <Point X="250.0" Y="310.0" T="1650477172"/>
      <Point X="251.0" Y="311.0" T="1650477172"/>
      <Point X="251.17582661096583" Y="311.0" T="1650477172"/>
      <Point X="252.0" Y="311.0" T="1650477172"/>
      <Point X="253.0" Y="311.0" T="1650477172"/>
      <Point X="254.0" Y="310.0" T="1650477172"/>
      <Point X="254.0" Y="309.0" T="1650477172"/>
      <Point X="254.0" Y="306.16880837039184" T="1650477172"/>
      <Point X="254.0" Y="303.0" T="1650477172"/>
      <Point X="254.6412826723374" Y="299.1523039659755" T="1650477172"/>
      <Point X="255.0" Y="297.0" T="1650477172"/>
      <Point X="255.48633301003935" Y="292.13666989960655" T="1650477172"/>
      <Point X="256.0" Y="287.0" T="1650477172"/>
      <Point X="256.85296567028695" Y="285.2940686594261" T="1650477172"/>
      <Point X="260.01457732617234" Y="278.9708453476553" T="1650477172"/>
      <Point X="261.0" Y="277.0" T="1650477172"/>
      <Point X="263.2899324685963" Y="272.70637662138193" T="1650477172"/>
      <Point X="266.61679297730944" Y="266.4685131675448" T="1650477172"/>
      <Point X="269.0" Y="262.0" T="1650477172"/>
      <Point X="270.2031581946788" Y="260.39578907376165" T="1650477172"/>
      <Point X="274.44490534328804" Y="254.74012620894933" T="1650477172"/>
      <Point X="278.0" Y="250.0" T="1650477172"/>
      <Point X="278.744779197148" Y="249.1310909366607" T="1650477172"/>
      <Point X="283.3455999516419" Y="243.7634667230845" T="1650477172"/>
      <Point X="284.0" Y="243.0" T="1650477172"/>
      <Point X="287.94642070613577" Y="238.39584250950827" T="1650477172"/>
      <Point X="290.0" Y="236.0" T="1650477172"/>
      <Point X="292.9456360936086" Y="233.42256841809248" T="1650477172"/>
      <Point X="298.0" Y="229.0" T="1650477172"/>
      <Point X="298.22630545196296" Y="228.72843345764446" T="1650477172"/>
      <Point X="302.7521393717312" Y="223.2974327539226" T="1650477172"/>
      <Point X="303.0" Y="223.0" T="1650477172"/>
      <Point X="308.13356794979927" Y="218.72202670850064" T="1650477172"/>
      <Point X="309.0" Y="218.0" T="1650477172"/>
      <Point X="312.0" Y="214.0" T="1650477172"/>
      <Point X="312.66590848289036" Y="213.33409151710964" T="1650477172"/>
      <Point X="315.0" Y="211.0" T="1650477172"/>
      <Point X="316.0" Y="209.0" T="1650477172"/>
      <Point X="317.5326067241992" Y="209.0" T="1650477172"/>
      <Point X="318.0" Y="209.0" T="1650477172"/>
      <Point X="319.0" Y="208.0" T="1650477172"/>
      <Point X="321.0" Y="206.0" T="1650477172"/>
      <Point X="322.0" Y="206.0" T="1650477172"/>
      <Point X="322.0" Y="205.0" T="1650477172"/>
      <Point X="322.0" Y="204.6404553819047" T="1650477172"/>
      <Point X="322.0" Y="204.0" T="1650477172"/>
      <Point X="321.0" Y="204.0" T="1650477172"/>
      <Point X="318.0" Y="203.0" T="1650477172"/>
      <Point X="315.73315446105767" Y="203.0" T="1650477172"/>
      <Point X="315.0" Y="203.0" T="1650477172"/>
      <Point X="310.0" Y="203.0" T="1650477172"/>
      <Point X="308.6635758800423" Y="203.0" T="1650477172"/>
      <Point X="304.0" Y="203.0" T="1650477172"/>
      <Point X="301.5939972990269" Y="203.0" T="1650477172"/>
      <Point X="294.52441871801153" Y="203.0" T="1650477172"/>
      <Point X="287.45484013699615" Y="203.0" T="1650477172"/>
      <Point X="287.0" Y="203.0" T="1650477172"/>
      <Point X="280.3852615559808" Y="203.0" T="1650477172"/>
      <Point X="273.3156829749654" Y="203.0" T="1650477172"/>
      <Point X="266.24610439395" Y="203.0" T="1650477172"/>
      <Point X="259.17652581293464" Y="203.0" T="1650477172"/>
      <Point X="253.0" Y="203.0" T="1650477172"/>
      <Point X="252.10694723191924" Y="203.0" T="1650477172"/>
      <Point X="245.03736865090383" Y="203.0" T="1650477172"/>
      <Point X="237.96779006988842" Y="203.0" T="1650477172"/>
      <Point X="230.89821148887302" Y="203.0" T="1650477172"/>
      <Point X="227.0" Y="203.0" T="1650477172"/>
      <Point X="223.8286329078576" Y="203.0" T="1650477172"/>
      <Point X="216.7590543268422" Y="203.0" T="1650477172"/>
      <Point X="209.6894757458268" Y="203.0" T="1650477172"/>
      <Point X="205.0" Y="203.0" T="1650477172"/>
      <Point X="202.6198971648114" Y="203.0" T="1650477172"/>
      <Point X="195.55031858379598" Y="203.0" T="1650477172"/>
      <Point X="188.48074000278058" Y="203.0" T="1650477172"/>
      <Point X="182.0" Y="203.0" T="1650477172"/>
      <Point X="181.41116142176517" Y="203.0" T="1650477172"/>
      <Point X="174.34158284074977" Y="203.0" T="1650477172"/>
      <Point X="170.0" Y="203.0" T="1650477172"/>
      <Point X="167.28868940549106" Y="202.6987432672768" T="1650477172"/>
      <Point X="161.0" Y="202.0" T="1650477172"/>
      <Point X="160.25781081685636" Y="202.0" T="1650477172"/>
      <Point X="154.0" Y="202.0" T="1650477172"/>
      <Point X="153.22988948024653" Y="201.7432964934155" T="1650477172"/>
      <Point X="151.0" Y="201.0" T="1650477172"/>
      <Point X="149.0" Y="201.0" T="1650477172"/>
    </Stroke>
  </Gesture>
