<?xml version="1.0" ?>
  <Gesture Name="exclamation03" Subject="20" Speed="medium" Number="3" NumPts="144" AppName="dollarstore-notepad" Date="2022-04-20" Time="1650477047">
    <Stroke>
      <Point X="225.0" Y="84.0" T="1650477047"/>
      <Point X="225.0" Y="86.72380952380952" T="1650477047"/>
      <Point X="225.0" Y="87.0" T="1650477047"/>
      <Point X="225.0" Y="89.44761904761904" T="1650477047"/>
      <Point X="225.0" Y="92.0" T="1650477047"/>
      <Point X="225.0" Y="92.17142857142856" T="1650477047"/>
      <Point X="225.0" Y="94.89523809523808" T="1650477047"/>
      <Point X="225.0" Y="97.6190476190476" T="1650477047"/>
      <Point X="225.0" Y="98.0" T="1650477047"/>
      <Point X="225.0" Y="100.34285714285713" T="1650477047"/>
      <Point X="225.0" Y="103.06666666666665" T="1650477047"/>
      <Point X="225.0" Y="105.79047619047617" T="1650477047"/>
      <Point X="225.0" Y="108.51428571428569" T="1650477047"/>
      <Point X="225.0" Y="111.23809523809521" T="1650477047"/>
      <Point X="225.0" Y="113.96190476190473" T="1650477047"/>
      <Point X="225.0" Y="114.0" T="1650477047"/>
      <Point X="225.0" Y="116.68571428571425" T="1650477047"/>
      <Point X="225.0" Y="119.40952380952378" T="1650477047"/>
      <Point X="225.0" Y="122.1333333333333" T="1650477047"/>
      <Point X="225.0" Y="124.85714285714282" T="1650477047"/>
      <Point X="225.0" Y="127.58095238095234" T="1650477047"/>
      <Point X="225.0" Y="130.30476190476188" T="1650477047"/>
      <Point X="225.0" Y="133.0285714285714" T="1650477047"/>
      <Point X="225.0" Y="135.0" T="1650477047"/>
      <Point X="225.0" Y="135.75238095238095" T="1650477047"/>
      <Point X="225.0" Y="138.47619047619048" T="1650477047"/>
      <Point X="225.0" Y="141.20000000000002" T="1650477047"/>
      <Point X="225.0" Y="143.92380952380955" T="1650477047"/>
      <Point X="225.0" Y="146.6476190476191" T="1650477047"/>
      <Point X="225.0" Y="149.37142857142862" T="1650477047"/>
      <Point X="225.0" Y="152.09523809523816" T="1650477047"/>
      <Point X="225.0" Y="154.8190476190477" T="1650477047"/>
      <Point X="225.0" Y="157.54285714285723" T="1650477047"/>
      <Point X="225.0" Y="160.0" T="1650477047"/>
      <Point X="225.0" Y="160.26666666666677" T="1650477047"/>
      <Point X="225.0" Y="162.9904761904763" T="1650477047"/>
      <Point X="225.0" Y="165.71428571428584" T="1650477047"/>
      <Point X="225.0" Y="168.43809523809537" T="1650477047"/>
      <Point X="225.0" Y="171.1619047619049" T="1650477047"/>
      <Point X="225.0" Y="173.88571428571444" T="1650477047"/>
      <Point X="225.0" Y="176.60952380952398" T="1650477047"/>
      <Point X="225.0" Y="179.3333333333335" T="1650477047"/>
      <Point X="225.0" Y="182.05714285714305" T="1650477047"/>
      <Point X="225.0" Y="184.78095238095258" T="1650477047"/>
      <Point X="225.0" Y="187.50476190476212" T="1650477047"/>
      <Point X="225.0" Y="190.22857142857166" T="1650477047"/>
      <Point X="225.0" Y="192.9523809523812" T="1650477047"/>
      <Point X="225.0" Y="195.67619047619073" T="1650477047"/>
      <Point X="225.0" Y="197.0" T="1650477047"/>
      <Point X="225.0" Y="198.40000000000026" T="1650477047"/>
      <Point X="225.0" Y="201.1238095238098" T="1650477047"/>
      <Point X="225.0" Y="203.84761904761933" T="1650477047"/>
      <Point X="225.0" Y="206.57142857142887" T="1650477047"/>
      <Point X="225.0" Y="209.2952380952384" T="1650477047"/>
      <Point X="225.0" Y="211.0" T="1650477047"/>
      <Point X="225.0" Y="212.01904761904794" T="1650477047"/>
      <Point X="225.0" Y="214.74285714285747" T="1650477047"/>
      <Point X="225.0" Y="217.466666666667" T="1650477047"/>
      <Point X="225.0" Y="220.19047619047655" T="1650477047"/>
      <Point X="225.0" Y="222.91428571428608" T="1650477047"/>
      <Point X="225.0" Y="225.63809523809562" T="1650477047"/>
      <Point X="225.0" Y="228.0" T="1650477047"/>
      <Point X="225.0" Y="228.36190476190515" T="1650477047"/>
      <Point X="225.0" Y="231.0857142857147" T="1650477047"/>
      <Point X="225.0" Y="233.80952380952422" T="1650477047"/>
      <Point X="225.0" Y="236.53333333333376" T="1650477047"/>
      <Point X="225.0" Y="239.2571428571433" T="1650477047"/>
      <Point X="225.0" Y="241.98095238095283" T="1650477047"/>
      <Point X="225.0" Y="244.70476190476236" T="1650477047"/>
      <Point X="225.0" Y="247.0" T="1650477047"/>
      <Point X="225.0" Y="247.4285714285719" T="1650477047"/>
      <Point X="225.0" Y="250.15238095238144" T="1650477047"/>
      <Point X="225.0" Y="252.0" T="1650477047"/>
      <Point X="225.0" Y="252.87619047619097" T="1650477047"/>
      <Point X="225.0" Y="255.6000000000005" T="1650477047"/>
      <Point X="225.0" Y="258.0" T="1650477047"/>
      <Point X="225.0" Y="258.32380952381004" T="1650477047"/>
      <Point X="225.0" Y="260.0" T="1650477047"/>
    </Stroke>
    <Stroke>
      <Point X="228.0" Y="334.0" T="1650477047"/>
      <Point X="228.0" Y="333.9845238095238" T="1650477047"/>
      <Point X="228.0" Y="333.9690476190476" T="1650477047"/>
      <Point X="228.0" Y="333.9535714285714" T="1650477047"/>
      <Point X="228.0" Y="333.93809523809523" T="1650477047"/>
      <Point X="228.0" Y="333.92261904761904" T="1650477047"/>
      <Point X="228.0" Y="333.90714285714284" T="1650477047"/>
      <Point X="228.0" Y="333.89166666666665" T="1650477047"/>
      <Point X="228.0" Y="333.87619047619046" T="1650477047"/>
      <Point X="228.0" Y="333.86071428571427" T="1650477047"/>
      <Point X="228.0" Y="333.8452380952381" T="1650477047"/>
      <Point X="228.0" Y="333.8297619047619" T="1650477047"/>
      <Point X="228.0" Y="333.8142857142857" T="1650477047"/>
      <Point X="228.0" Y="333.7988095238095" T="1650477047"/>
      <Point X="228.0" Y="333.7833333333333" T="1650477047"/>
      <Point X="228.0" Y="333.7678571428571" T="1650477047"/>
      <Point X="228.0" Y="333.7523809523809" T="1650477047"/>
      <Point X="228.0" Y="333.7369047619047" T="1650477047"/>
      <Point X="228.0" Y="333.72142857142853" T="1650477047"/>
      <Point X="228.0" Y="333.70595238095234" T="1650477047"/>
      <Point X="228.0" Y="333.69047619047615" T="1650477047"/>
      <Point X="228.0" Y="333.67499999999995" T="1650477047"/>
      <Point X="228.0" Y="333.65952380952376" T="1650477047"/>
      <Point X="228.0" Y="333.64404761904757" T="1650477047"/>
      <Point X="228.0" Y="333.6285714285714" T="1650477047"/>
      <Point X="228.0" Y="333.6130952380952" T="1650477047"/>
      <Point X="228.0" Y="333.597619047619" T="1650477047"/>
      <Point X="228.0" Y="333.5821428571428" T="1650477047"/>
      <Point X="228.0" Y="333.5666666666666" T="1650477047"/>
      <Point X="228.0" Y="333.5511904761904" T="1650477047"/>
      <Point X="228.0" Y="333.5357142857142" T="1650477047"/>
      <Point X="228.0" Y="333.520238095238" T="1650477047"/>
      <Point X="228.0" Y="333.50476190476184" T="1650477047"/>
      <Point X="228.0" Y="333.48928571428564" T="1650477047"/>
      <Point X="228.0" Y="333.47380952380945" T="1650477047"/>
      <Point X="228.0" Y="333.45833333333326" T="1650477047"/>
      <Point X="228.0" Y="333.44285714285706" T="1650477047"/>
      <Point X="228.0" Y="333.4273809523809" T="1650477047"/>
      <Point X="228.0" Y="333.4119047619047" T="1650477047"/>
      <Point X="228.0" Y="333.3964285714285" T="1650477047"/>
      <Point X="228.0" Y="333.3809523809523" T="1650477047"/>
      <Point X="228.0" Y="333.3654761904761" T="1650477047"/>
      <Point X="228.0" Y="333.3499999999999" T="1650477047"/>
      <Point X="228.0" Y="333.3345238095237" T="1650477047"/>
      <Point X="228.0" Y="333.3190476190475" T="1650477047"/>
      <Point X="228.0" Y="333.30357142857133" T="1650477047"/>
      <Point X="228.0" Y="333.28809523809514" T="1650477047"/>
      <Point X="228.0" Y="333.27261904761895" T="1650477047"/>
      <Point X="228.0" Y="333.25714285714275" T="1650477047"/>
      <Point X="228.0" Y="333.24166666666656" T="1650477047"/>
      <Point X="228.0" Y="333.22619047619037" T="1650477047"/>
      <Point X="228.0" Y="333.2107142857142" T="1650477047"/>
      <Point X="228.0" Y="333.195238095238" T="1650477047"/>
      <Point X="228.0" Y="333.1797619047618" T="1650477047"/>
      <Point X="228.0" Y="333.1642857142856" T="1650477047"/>
      <Point X="228.0" Y="333.1488095238094" T="1650477047"/>
      <Point X="228.0" Y="333.1333333333332" T="1650477047"/>
      <Point X="228.0" Y="333.117857142857" T="1650477047"/>
      <Point X="228.0" Y="333.1023809523808" T="1650477047"/>
      <Point X="228.0" Y="333.08690476190463" T="1650477047"/>
      <Point X="228.0" Y="333.07142857142844" T="1650477047"/>
      <Point X="228.0" Y="333.05595238095225" T="1650477047"/>
      <Point X="228.0" Y="333.04047619047606" T="1650477047"/>
      <Point X="228.0" Y="333.02499999999986" T="1650477047"/>
      <Point X="228.0" Y="333.00952380952367" T="1650477047"/>
      <Point X="228.0" Y="333.0" T="1650477047"/>
    </Stroke>
  </Gesture>
