<?xml version="1.0" ?>
  <Gesture Name="N03" Subject="20" Speed="medium" Number="3" NumPts="240" AppName="dollarstore-notepad" Date="2022-04-20" Time="1650477047">
    <Stroke>
      <Point X="130.0" Y="291.0" T="1650477047"/>
      <Point X="130.0" Y="288.0904761904762" T="1650477047"/>
      <Point X="130.0" Y="288.0" T="1650477047"/>
      <Point X="130.0" Y="285.18095238095236" T="1650477047"/>
      <Point X="130.0" Y="283.0" T="1650477047"/>
      <Point X="130.0" Y="282.27142857142854" T="1650477047"/>
      <Point X="130.0" Y="279.3619047619047" T="1650477047"/>
      <Point X="130.0" Y="276.4523809523809" T="1650477047"/>
      <Point X="130.0" Y="273.5428571428571" T="1650477047"/>
      <Point X="130.0" Y="270.63333333333327" T="1650477047"/>
      <Point X="130.0" Y="267.72380952380945" T="1650477047"/>
      <Point X="130.0" Y="267.0" T="1650477047"/>
      <Point X="130.0" Y="264.81428571428563" T="1650477047"/>
      <Point X="130.0" Y="261.9047619047618" T="1650477047"/>
      <Point X="130.0" Y="258.995238095238" T="1650477047"/>
      <Point X="130.0" Y="256.0857142857142" T="1650477047"/>
      <Point X="130.0" Y="253.17619047619036" T="1650477047"/>
      <Point X="130.0" Y="250.26666666666654" T="1650477047"/>
      <Point X="130.0" Y="247.35714285714272" T="1650477047"/>
      <Point X="130.0" Y="244.4476190476189" T="1650477047"/>
      <Point X="130.0" Y="241.53809523809508" T="1650477047"/>
      <Point X="130.0" Y="238.62857142857126" T="1650477047"/>
      <Point X="130.0" Y="236.0" T="1650477047"/>
      <Point X="130.0" Y="235.71904761904744" T="1650477047"/>
      <Point X="130.0" Y="232.80952380952363" T="1650477047"/>
      <Point X="130.0" Y="229.8999999999998" T="1650477047"/>
      <Point X="130.0" Y="228.0" T="1650477047"/>
      <Point X="130.0" Y="226.990476190476" T="1650477047"/>
      <Point X="130.0" Y="224.08095238095217" T="1650477047"/>
      <Point X="130.0" Y="221.17142857142835" T="1650477047"/>
      <Point X="130.0" Y="218.26190476190453" T="1650477047"/>
      <Point X="130.0" Y="215.3523809523807" T="1650477047"/>
      <Point X="130.0" Y="212.4428571428569" T="1650477047"/>
      <Point X="130.0" Y="209.53333333333308" T="1650477047"/>
      <Point X="130.0" Y="208.0" T="1650477047"/>
      <Point X="130.0" Y="206.62380952380926" T="1650477047"/>
      <Point X="130.0" Y="203.71428571428544" T="1650477047"/>
      <Point X="130.0" Y="200.80476190476162" T="1650477047"/>
      <Point X="130.0" Y="197.8952380952378" T="1650477047"/>
      <Point X="130.0" Y="194.98571428571398" T="1650477047"/>
      <Point X="130.0" Y="192.07619047619016" T="1650477047"/>
      <Point X="130.0" Y="189.16666666666634" T="1650477047"/>
      <Point X="130.0" Y="186.25714285714253" T="1650477047"/>
      <Point X="130.0" Y="186.0" T="1650477047"/>
      <Point X="130.0" Y="183.3476190476187" T="1650477047"/>
      <Point X="130.0" Y="180.4380952380949" T="1650477047"/>
      <Point X="130.0" Y="177.52857142857107" T="1650477047"/>
      <Point X="130.0" Y="174.61904761904725" T="1650477047"/>
      <Point X="130.0" Y="171.70952380952343" T="1650477047"/>
      <Point X="130.0" Y="168.7999999999996" T="1650477047"/>
      <Point X="130.0" Y="165.8904761904758" T="1650477047"/>
      <Point X="130.0" Y="162.98095238095198" T="1650477047"/>
      <Point X="130.0" Y="160.07142857142816" T="1650477047"/>
      <Point X="130.0" Y="157.16190476190434" T="1650477047"/>
      <Point X="130.0" Y="157.0" T="1650477047"/>
      <Point X="130.0" Y="154.25238095238052" T="1650477047"/>
      <Point X="130.0" Y="151.3428571428567" T="1650477047"/>
      <Point X="130.0" Y="148.43333333333288" T="1650477047"/>
      <Point X="130.0" Y="145.52380952380906" T="1650477047"/>
      <Point X="130.0" Y="142.61428571428524" T="1650477047"/>
      <Point X="130.0" Y="139.70476190476143" T="1650477047"/>
      <Point X="130.0" Y="136.7952380952376" T="1650477047"/>
      <Point X="130.0" Y="133.8857142857138" T="1650477047"/>
      <Point X="130.0" Y="130.97619047618997" T="1650477047"/>
      <Point X="130.0" Y="128.06666666666615" T="1650477047"/>
      <Point X="130.0" Y="127.0" T="1650477047"/>
      <Point X="130.0" Y="125.15714285714235" T="1650477047"/>
      <Point X="130.0" Y="124.0" T="1650477047"/>
      <Point X="130.0" Y="122.24761904761854" T="1650477047"/>
      <Point X="130.0" Y="119.33809523809474" T="1650477047"/>
      <Point X="130.0" Y="116.42857142857093" T="1650477047"/>
      <Point X="130.0" Y="113.51904761904713" T="1650477047"/>
      <Point X="130.0" Y="113.0" T="1650477047"/>
      <Point X="130.0" Y="110.60952380952332" T="1650477047"/>
      <Point X="130.0" Y="107.69999999999952" T="1650477047"/>
      <Point X="130.0" Y="107.0" T="1650477047"/>
      <Point X="130.0" Y="105.0" T="1650477047"/>
      <Point X="130.0" Y="104.79047619047572" T="1650477047"/>
      <Point X="130.0" Y="103.0" T="1650477047"/>
    </Stroke>
    <Stroke>
      <Point X="149.0" Y="104.0" T="1650477047"/>
      <Point X="149.0" Y="105.0" T="1650477047"/>
      <Point X="149.0" Y="107.0" T="1650477047"/>
      <Point X="149.44897408826463" Y="107.98774299418221" T="1650477047"/>
      <Point X="151.13935700943284" Y="111.70658542075225" T="1650477047"/>
      <Point X="152.82973993060105" Y="115.42542784732228" T="1650477047"/>
      <Point X="154.0" Y="118.0" T="1650477047"/>
      <Point X="154.646687035995" Y="119.07781172665831" T="1650477047"/>
      <Point X="156.7483995780769" Y="122.5806659634615" T="1650477047"/>
      <Point X="157.0" Y="123.0" T="1650477047"/>
      <Point X="158.60816738448452" Y="126.21633476896903" T="1650477047"/>
      <Point X="160.43503264573584" Y="129.8700652914717" T="1650477047"/>
      <Point X="162.26189790698717" Y="133.52379581397435" T="1650477047"/>
      <Point X="164.0" Y="137.0" T="1650477047"/>
      <Point X="164.0887631682385" Y="137.177526336477" T="1650477047"/>
      <Point X="165.91562842948983" Y="140.83125685897966" T="1650477047"/>
      <Point X="167.74249369074116" Y="144.4849873814823" T="1650477047"/>
      <Point X="169.56935895199248" Y="148.13871790398497" T="1650477047"/>
      <Point X="171.0" Y="151.0" T="1650477047"/>
      <Point X="171.46434207778233" Y="151.7545558763963" T="1650477047"/>
      <Point X="173.60527739390807" Y="155.2335757651006" T="1650477047"/>
      <Point X="175.74621271003377" Y="158.7125956538049" T="1650477047"/>
      <Point X="177.8871480261595" Y="162.1916155425092" T="1650477047"/>
      <Point X="180.02808334228524" Y="165.6706354312135" T="1650477047"/>
      <Point X="182.16901865841095" Y="169.1496553199178" T="1650477047"/>
      <Point X="184.30995397453668" Y="172.6286752086221" T="1650477047"/>
      <Point X="186.4508892906624" Y="176.1076950973264" T="1650477047"/>
      <Point X="187.0" Y="177.0" T="1650477047"/>
      <Point X="188.56266175614095" Y="179.6044362602349" T="1650477047"/>
      <Point X="190.66437429822287" Y="183.1072904970381" T="1650477047"/>
      <Point X="192.76608684030478" Y="186.61014473384128" T="1650477047"/>
      <Point X="194.8677993823867" Y="190.11299897064447" T="1650477047"/>
      <Point X="196.0" Y="192.0" T="1650477047"/>
      <Point X="196.91514187987872" Y="193.64725538378167" T="1650477047"/>
      <Point X="198.8989907817679" Y="197.21818340718224" T="1650477047"/>
      <Point X="200.8828396836571" Y="200.7891114305828" T="1650477047"/>
      <Point X="202.8666885855463" Y="204.36003945398335" T="1650477047"/>
      <Point X="204.8505374874355" Y="207.93096747738392" T="1650477047"/>
      <Point X="206.0" Y="210.0" T="1650477047"/>
      <Point X="206.91059474668336" Y="211.45695159469338" T="1650477047"/>
      <Point X="209.07563771884392" Y="214.92102035015026" T="1650477047"/>
      <Point X="211.0" Y="218.0" T="1650477047"/>
      <Point X="211.2596598644623" Y="218.3725554577068" T="1650477047"/>
      <Point X="213.59542997697145" Y="221.723877793046" T="1650477047"/>
      <Point X="215.9312000894806" Y="225.0752001283852" T="1650477047"/>
      <Point X="218.26697020198975" Y="228.4265224637244" T="1650477047"/>
      <Point X="220.6027403144989" Y="231.77784479906362" T="1650477047"/>
      <Point X="222.93851042700805" Y="235.12916713440282" T="1650477047"/>
      <Point X="225.27428053951718" Y="238.48048946974203" T="1650477047"/>
      <Point X="227.61005065202633" Y="241.83181180508123" T="1650477047"/>
      <Point X="229.94582076453545" Y="245.18313414042044" T="1650477047"/>
      <Point X="232.2815908770446" Y="248.53445647575964" T="1650477047"/>
      <Point X="234.0" Y="251.0" T="1650477047"/>
      <Point X="234.65948070031385" Y="251.85488238929574" T="1650477047"/>
      <Point X="237.1546097020397" Y="255.08930887301443" T="1650477047"/>
      <Point X="239.64973870376554" Y="258.32373535673315" T="1650477047"/>
      <Point X="242.1448677054914" Y="261.5581618404519" T="1650477047"/>
      <Point X="244.63999670721728" Y="264.7925883241706" T="1650477047"/>
      <Point X="247.13512570894315" Y="268.0270148078893" T="1650477047"/>
      <Point X="249.63025471066902" Y="271.26144129160804" T="1650477047"/>
      <Point X="252.1253837123949" Y="274.49586777532676" T="1650477047"/>
      <Point X="254.62051271412076" Y="277.7302942590455" T="1650477047"/>
      <Point X="257.1156417158466" Y="280.9647207427642" T="1650477047"/>
      <Point X="259.6107707175725" Y="284.19914722648286" T="1650477047"/>
      <Point X="261.0" Y="286.0" T="1650477047"/>
      <Point X="262.11157975185193" Y="287.4291739666668" T="1650477047"/>
      <Point X="264.61952403303565" Y="290.65367375676016" T="1650477047"/>
      <Point X="267.1274683142194" Y="293.87817354685353" T="1650477047"/>
      <Point X="268.0" Y="295.0" T="1650477047"/>
      <Point X="269.88358826699346" Y="296.88358826699346" T="1650477047"/>
      <Point X="272.77211586888984" Y="299.77211586888984" T="1650477047"/>
      <Point X="275.6606434707862" Y="302.6606434707862" T="1650477047"/>
      <Point X="278.5491710726826" Y="305.5491710726826" T="1650477047"/>
      <Point X="281.437698674579" Y="308.437698674579" T="1650477047"/>
      <Point X="282.0" Y="309.0" T="1650477047"/>
      <Point X="284.01973001157944" Y="311.5967957291736" T="1650477047"/>
      <Point X="286.5276742927632" Y="314.821295519267" T="1650477047"/>
      <Point X="289.0" Y="318.0" T="1650477047"/>
      <Point X="289.0410237319696" Y="318.0410237319696" T="1650477047"/>
      <Point X="291.92955133386596" Y="320.92955133386596" T="1650477047"/>
      <Point X="293.0" Y="322.0" T="1650477047"/>
      <Point X="293.0" Y="323.0" T="1650477047"/>
    </Stroke>
    <Stroke>
      <Point X="325.0" Y="325.0" T="1650477047"/>
      <Point X="325.0" Y="324.0" T="1650477047"/>
      <Point X="325.0" Y="320.3637834521765" T="1650477047"/>
      <Point X="325.0" Y="320.0" T="1650477047"/>
      <Point X="325.0" Y="315.727566904353" T="1650477047"/>
      <Point X="325.0" Y="311.0913503565295" T="1650477047"/>
      <Point X="325.0" Y="311.0" T="1650477047"/>
      <Point X="325.0" Y="306.455133808706" T="1650477047"/>
      <Point X="325.0" Y="301.81891726088253" T="1650477047"/>
      <Point X="325.0" Y="301.0" T="1650477047"/>
      <Point X="325.0" Y="297.18270071305903" T="1650477047"/>
      <Point X="325.0" Y="292.54648416523554" T="1650477047"/>
      <Point X="325.0" Y="287.91026761741205" T="1650477047"/>
      <Point X="325.0" Y="286.0" T="1650477047"/>
      <Point X="325.0" Y="283.27405106958855" T="1650477047"/>
      <Point X="325.0" Y="278.63783452176506" T="1650477047"/>
      <Point X="325.0" Y="274.00161797394156" T="1650477047"/>
      <Point X="325.0" Y="272.0" T="1650477047"/>
      <Point X="325.0" Y="269.36540142611807" T="1650477047"/>
      <Point X="325.0" Y="264.7291848782946" T="1650477047"/>
      <Point X="325.0" Y="260.0929683304711" T="1650477047"/>
      <Point X="325.0" Y="255.4567517826476" T="1650477047"/>
      <Point X="325.0" Y="250.8205352348241" T="1650477047"/>
      <Point X="325.0" Y="246.1843186870006" T="1650477047"/>
      <Point X="325.0" Y="243.0" T="1650477047"/>
      <Point X="325.0" Y="241.5481021391771" T="1650477047"/>
      <Point X="325.0" Y="236.9118855913536" T="1650477047"/>
      <Point X="325.0" Y="234.0" T="1650477047"/>
      <Point X="325.1075608098289" Y="232.27902704273737" T="1650477047"/>
      <Point X="325.39676005232644" Y="227.6518391627771" T="1650477047"/>
      <Point X="325.68595929482393" Y="223.02465128281682" T="1650477047"/>
      <Point X="325.9751585373215" Y="218.39746340285654" T="1650477047"/>
      <Point X="326.26435777981897" Y="213.77027552289627" T="1650477047"/>
      <Point X="326.5535570223165" Y="209.143087642936" T="1650477047"/>
      <Point X="326.842756264814" Y="204.51589976297572" T="1650477047"/>
      <Point X="327.13195550731155" Y="199.88871188301545" T="1650477047"/>
      <Point X="327.42115474980903" Y="195.26152400305517" T="1650477047"/>
      <Point X="327.7103539923066" Y="190.6343361230949" T="1650477047"/>
      <Point X="327.99955323480407" Y="186.00714824313462" T="1650477047"/>
      <Point X="328.2887524773016" Y="181.37996036317435" T="1650477047"/>
      <Point X="328.5779517197991" Y="176.75277248321407" T="1650477047"/>
      <Point X="328.86715096229665" Y="172.1255846032538" T="1650477047"/>
      <Point X="329.0" Y="170.0" T="1650477047"/>
      <Point X="329.2544424813279" Y="167.50646368298686" T="1650477047"/>
      <Point X="329.72508192152617" Y="162.8941971690436" T="1650477047"/>
      <Point X="330.19572136172445" Y="158.28193065510033" T="1650477047"/>
      <Point X="330.66636080192274" Y="153.66966414115706" T="1650477047"/>
      <Point X="331.137000242121" Y="149.0573976272138" T="1650477047"/>
      <Point X="331.6076396823193" Y="144.44513111327052" T="1650477047"/>
      <Point X="332.0782791225176" Y="139.83286459932725" T="1650477047"/>
      <Point X="332.54891856271587" Y="135.22059808538398" T="1650477047"/>
      <Point X="333.01955800291415" Y="130.60833157144071" T="1650477047"/>
      <Point X="333.4901974431125" Y="125.99606505749746" T="1650477047"/>
      <Point X="333.9608368833108" Y="121.3837985435542" T="1650477047"/>
      <Point X="334.0" Y="121.0" T="1650477047"/>
      <Point X="334.3848154038441" Y="116.76703055771492" T="1650477047"/>
      <Point X="334.80455872781596" Y="112.14985399402434" T="1650477047"/>
      <Point X="335.22430205178784" Y="107.53267743033376" T="1650477047"/>
      <Point X="335.64404537575973" Y="102.91550086664319" T="1650477047"/>
      <Point X="336.0637886997316" Y="98.29832430295261" T="1650477047"/>
      <Point X="336.48353202370345" Y="93.68114773926203" T="1650477047"/>
      <Point X="336.90327534767533" Y="89.06397117557145" T="1650477047"/>
      <Point X="337.0" Y="88.0" T="1650477047"/>
      <Point X="337.19790914459685" Y="84.43763539725698" T="1650477047"/>
      <Point X="337.45508016747885" Y="79.80855698538035" T="1650477047"/>
      <Point X="337.7122511903609" Y="75.17947857350372" T="1650477047"/>
      <Point X="337.9694222132429" Y="70.55040016162708" T="1650477047"/>
      <Point X="338.226593236125" Y="65.92132174975045" T="1650477047"/>
      <Point X="338.483764259007" Y="61.29224333787381" T="1650477047"/>
      <Point X="338.74093528188905" Y="56.66316492599718" T="1650477047"/>
      <Point X="338.99810630477106" Y="52.034086514120546" T="1650477047"/>
      <Point X="339.0" Y="52.0" T="1650477047"/>
      <Point X="339.0" Y="47.397922528416345" T="1650477047"/>
      <Point X="339.0" Y="42.76170598059284" T="1650477047"/>
      <Point X="339.0" Y="41.0" T="1650477047"/>
      <Point X="339.0" Y="38.12548943276934" T="1650477047"/>
      <Point X="339.0" Y="33.48927288494584" T="1650477047"/>
      <Point X="339.0" Y="28.85305633712234" T="1650477047"/>
      <Point X="339.0" Y="26.0" T="1650477047"/>
    </Stroke>
  </Gesture>
