<?xml version="1.0" ?>
  <Gesture Name="T05" Subject="5" Speed="medium" Number="5" NumPts="169" AppName="dollarstore-notepad" Date="2022-04-19" Time="1650426742">
    <Stroke>
      <Point X="163.0" Y="157.0" T="1650426742"/>
      <Point X="164.0" Y="157.0" T="1650426742"/>
      <Point X="165.21530990872833" Y="157.0" T="1650426742"/>
      <Point X="167.43061981745666" Y="157.0" T="1650426742"/>
      <Point X="169.0" Y="157.0" T="1650426742"/>
      <Point X="169.645929726185" Y="157.0" T="1650426742"/>
      <Point X="171.86123963491332" Y="157.0" T="1650426742"/>
      <Point X="174.07654954364165" Y="157.0" T="1650426742"/>
      <Point X="176.29185945236998" Y="157.0" T="1650426742"/>
      <Point X="178.5071693610983" Y="157.0" T="1650426742"/>
      <Point X="180.72247926982664" Y="157.0" T="1650426742"/>
      <Point X="182.93778917855497" Y="157.0" T="1650426742"/>
      <Point X="185.1530990872833" Y="157.0" T="1650426742"/>
      <Point X="187.36840899601162" Y="157.0" T="1650426742"/>
      <Point X="189.58371890473995" Y="157.0" T="1650426742"/>
      <Point X="191.79902881346828" Y="157.0" T="1650426742"/>
      <Point X="194.0" Y="157.0" T="1650426742"/>
      <Point X="194.0143387221966" Y="157.0" T="1650426742"/>
      <Point X="196.22964863092494" Y="157.0" T="1650426742"/>
      <Point X="198.44495853965327" Y="157.0" T="1650426742"/>
      <Point X="200.6602684483816" Y="157.0" T="1650426742"/>
      <Point X="202.87557835710993" Y="157.0" T="1650426742"/>
      <Point X="205.09088826583826" Y="157.0" T="1650426742"/>
      <Point X="207.3061981745666" Y="157.0" T="1650426742"/>
      <Point X="209.52150808329492" Y="157.0" T="1650426742"/>
      <Point X="211.73681799202325" Y="157.0" T="1650426742"/>
      <Point X="213.95212790075158" Y="157.0" T="1650426742"/>
      <Point X="216.1674378094799" Y="157.0" T="1650426742"/>
      <Point X="217.0" Y="157.0" T="1650426742"/>
      <Point X="218.38274771820824" Y="157.0" T="1650426742"/>
      <Point X="220.59805762693657" Y="157.0" T="1650426742"/>
      <Point X="222.8133675356649" Y="157.0" T="1650426742"/>
      <Point X="223.0" Y="157.0" T="1650426742"/>
      <Point X="225.00828820887892" Y="156.71310168444586" T="1650426742"/>
      <Point X="227.20133313132712" Y="156.39980955266756" T="1650426742"/>
      <Point X="229.3943780537753" Y="156.08651742088924" T="1650426742"/>
      <Point X="231.5874229762235" Y="155.77322528911094" T="1650426742"/>
      <Point X="233.7804678986717" Y="155.4599331573326" T="1650426742"/>
      <Point X="235.9735128211199" Y="155.1466410255543" T="1650426742"/>
      <Point X="237.0" Y="155.0" T="1650426742"/>
      <Point X="238.1784012730324" Y="155.0" T="1650426742"/>
      <Point X="240.39371118176072" Y="155.0" T="1650426742"/>
      <Point X="242.60902109048905" Y="155.0" T="1650426742"/>
      <Point X="244.82433099921738" Y="155.0" T="1650426742"/>
      <Point X="247.0" Y="155.0" T="1650426742"/>
      <Point X="247.0393347959674" Y="154.9950831505041" T="1650426742"/>
      <Point X="249.2375378084631" Y="154.72030777394212" T="1650426742"/>
      <Point X="251.43574082095878" Y="154.44553239738016" T="1650426742"/>
      <Point X="253.63394383345448" Y="154.1707570208182" T="1650426742"/>
      <Point X="255.0" Y="154.0" T="1650426742"/>
      <Point X="255.82721242894164" Y="153.86213126184307" T="1650426742"/>
      <Point X="258.0123806623164" Y="153.4979365562806" T="1650426742"/>
      <Point X="260.19754889569117" Y="153.13374185071814" T="1650426742"/>
      <Point X="261.0" Y="153.0" T="1650426742"/>
      <Point X="262.3599360460113" Y="152.66001598849718" T="1650426742"/>
      <Point X="264.5091023394617" Y="152.12272441513457" T="1650426742"/>
      <Point X="265.0" Y="152.0" T="1650426742"/>
      <Point X="266.70930418228636" Y="152.0" T="1650426742"/>
      <Point X="268.0" Y="152.0" T="1650426742"/>
      <Point X="268.9246140910147" Y="152.0" T="1650426742"/>
      <Point X="269.0" Y="152.0" T="1650426742"/>
      <Point X="270.9140062120435" Y="151.04299689397826" T="1650426742"/>
      <Point X="271.0" Y="151.0" T="1650426742"/>
      <Point X="273.0376287916538" Y="150.41782034524178" T="1650426742"/>
      <Point X="275.1677023203421" Y="149.8092279084737" T="1650426742"/>
      <Point X="277.29777584903036" Y="149.2006354717056" T="1650426742"/>
      <Point X="278.0" Y="149.0" T="1650426742"/>
      <Point X="279.45614834765536" Y="148.70877033046892" T="1650426742"/>
      <Point X="281.62843843482096" Y="148.2743123130358" T="1650426742"/>
      <Point X="283.0" Y="148.0" T="1650426742"/>
      <Point X="283.8115916146634" Y="147.90982315392628" T="1650426742"/>
      <Point X="286.01335210020983" Y="147.66518309997667" T="1650426742"/>
      <Point X="288.21511258575623" Y="147.4205430460271" T="1650426742"/>
      <Point X="290.41687307130263" Y="147.17590299207748" T="1650426742"/>
      <Point X="292.0" Y="147.0" T="1650426742"/>
      <Point X="292.6176340057075" Y="146.92279574928656" T="1650426742"/>
      <Point X="294.8158370182032" Y="146.6480203727246" T="1650426742"/>
      <Point X="297.0140400306989" Y="146.37324499616264" T="1650426742"/>
      <Point X="299.2122430431946" Y="146.09846961960068" T="1650426742"/>
      <Point X="300.0" Y="146.0" T="1650426742"/>
      <Point X="301.42142245513077" Y="146.0" T="1650426742"/>
      <Point X="303.6367323638591" Y="146.0" T="1650426742"/>
      <Point X="305.0" Y="146.0" T="1650426742"/>
    </Stroke>
    <Stroke>
      <Point X="236.0" Y="157.0" T="1650426742"/>
      <Point X="236.0" Y="158.0" T="1650426742"/>
      <Point X="235.96361047011086" Y="158.67320630294924" T="1650426742"/>
      <Point X="235.87324568220671" Y="160.344954879176" T="1650426742"/>
      <Point X="235.78288089430256" Y="162.01670345540273" T="1650426742"/>
      <Point X="235.69251610639841" Y="163.68845203162948" T="1650426742"/>
      <Point X="235.60215131849426" Y="165.36020060785623" T="1650426742"/>
      <Point X="235.51178653059011" Y="167.03194918408298" T="1650426742"/>
      <Point X="235.42142174268596" Y="168.70369776030972" T="1650426742"/>
      <Point X="235.33105695478181" Y="170.37544633653647" T="1650426742"/>
      <Point X="235.24069216687766" Y="172.04719491276322" T="1650426742"/>
      <Point X="235.15032737897351" Y="173.71894348898996" T="1650426742"/>
      <Point X="235.05996259106936" Y="175.3906920652167" T="1650426742"/>
      <Point X="234.96959780316521" Y="177.06244064144346" T="1650426742"/>
      <Point X="234.87923301526106" Y="178.7341892176702" T="1650426742"/>
      <Point X="234.78886822735691" Y="180.40593779389695" T="1650426742"/>
      <Point X="234.69850343945276" Y="182.0776863701237" T="1650426742"/>
      <Point X="234.60813865154861" Y="183.74943494635045" T="1650426742"/>
      <Point X="234.51777386364446" Y="185.4211835225772" T="1650426742"/>
      <Point X="234.42740907574031" Y="187.09293209880394" T="1650426742"/>
      <Point X="234.33704428783616" Y="188.7646806750307" T="1650426742"/>
      <Point X="234.24667949993201" Y="190.43642925125744" T="1650426742"/>
      <Point X="234.15631471202786" Y="192.10817782748418" T="1650426742"/>
      <Point X="234.06594992412371" Y="193.77992640371093" T="1650426742"/>
      <Point X="234.0" Y="195.0" T="1650426742"/>
      <Point X="233.9624356760343" Y="195.4507718875885" T="1650426742"/>
      <Point X="233.8234018399886" Y="197.1191779201368" T="1650426742"/>
      <Point X="233.68436800394292" Y="198.78758395268508" T="1650426742"/>
      <Point X="233.54533416789724" Y="200.45598998523337" T="1650426742"/>
      <Point X="233.40630033185155" Y="202.12439601778166" T="1650426742"/>
      <Point X="233.26726649580584" Y="203.79280205032995" T="1650426742"/>
      <Point X="233.12823265976016" Y="205.46120808287824" T="1650426742"/>
      <Point X="233.0" Y="207.0" T="1650426742"/>
      <Point X="233.0" Y="207.1300633858046" T="1650426742"/>
      <Point X="233.0" Y="208.80425247220109" T="1650426742"/>
      <Point X="233.0" Y="210.47844155859758" T="1650426742"/>
      <Point X="233.0" Y="211.0" T="1650426742"/>
      <Point X="233.0" Y="212.15263064499408" T="1650426742"/>
      <Point X="233.0" Y="213.82681973139057" T="1650426742"/>
      <Point X="233.0" Y="215.50100881778707" T="1650426742"/>
      <Point X="233.0" Y="217.17519790418356" T="1650426742"/>
      <Point X="233.0" Y="218.84938699058006" T="1650426742"/>
      <Point X="233.0" Y="219.0" T="1650426742"/>
      <Point X="232.7495256358624" Y="220.50284618482567" T="1650426742"/>
      <Point X="232.47429064550113" Y="222.15425612699326" T="1650426742"/>
      <Point X="232.19905565513986" Y="223.80566606916085" T="1650426742"/>
      <Point X="232.0" Y="225.0" T="1650426742"/>
      <Point X="232.0" Y="225.46338080586779" T="1650426742"/>
      <Point X="232.0" Y="227.13756989226428" T="1650426742"/>
      <Point X="232.0" Y="228.81175897866078" T="1650426742"/>
      <Point X="232.0" Y="229.0" T="1650426742"/>
      <Point X="232.0" Y="230.48594806505727" T="1650426742"/>
      <Point X="232.0" Y="232.16013715145377" T="1650426742"/>
      <Point X="232.0" Y="233.0" T="1650426742"/>
      <Point X="232.0" Y="233.83432623785026" T="1650426742"/>
      <Point X="232.0" Y="235.50851532424676" T="1650426742"/>
      <Point X="232.0" Y="237.18270441064325" T="1650426742"/>
      <Point X="232.0" Y="238.0" T="1650426742"/>
      <Point X="232.0" Y="238.85689349703975" T="1650426742"/>
      <Point X="232.0" Y="240.0" T="1650426742"/>
      <Point X="232.0" Y="240.53108258343624" T="1650426742"/>
      <Point X="232.0" Y="242.20527166983274" T="1650426742"/>
      <Point X="232.0" Y="243.0" T="1650426742"/>
      <Point X="232.0" Y="243.87946075622924" T="1650426742"/>
      <Point X="232.0" Y="245.0" T="1650426742"/>
      <Point X="232.0" Y="245.55364984262573" T="1650426742"/>
      <Point X="232.0" Y="247.22783892902223" T="1650426742"/>
      <Point X="232.0" Y="248.0" T="1650426742"/>
      <Point X="232.0" Y="248.90202801541872" T="1650426742"/>
      <Point X="232.0" Y="249.0" T="1650426742"/>
      <Point X="232.0" Y="250.57621710181522" T="1650426742"/>
      <Point X="232.0" Y="251.0" T="1650426742"/>
      <Point X="232.0" Y="252.0" T="1650426742"/>
      <Point X="232.0" Y="252.2504061882117" T="1650426742"/>
      <Point X="232.0" Y="253.9245952746082" T="1650426742"/>
      <Point X="232.0" Y="255.0" T="1650426742"/>
      <Point X="232.0" Y="255.5987843610047" T="1650426742"/>
      <Point X="232.0" Y="257.27297344740117" T="1650426742"/>
      <Point X="232.0" Y="258.0" T="1650426742"/>
      <Point X="232.0" Y="258.94716253379767" T="1650426742"/>
      <Point X="232.0" Y="260.0" T="1650426742"/>
      <Point X="232.0" Y="260.62135162019416" T="1650426742"/>
      <Point X="232.0" Y="262.29554070659066" T="1650426742"/>
      <Point X="232.0" Y="263.0" T="1650426742"/>
      <Point X="232.0" Y="263.96972979298715" T="1650426742"/>
      <Point X="232.0" Y="265.0" T="1650426742"/>
    </Stroke>
  </Gesture>
