<?xml version="1.0" ?>
  <Gesture Name="pitchfork02" Subject="3" Speed="medium" Number="2" NumPts="175" AppName="dollarstore-notepad" Date="2022-04-22" Time="1650653648">
    <Stroke>
      <Point X="244.0" Y="216.0" T="1650653648"/>
      <Point X="244.0" Y="217.0" T="1650653648"/>
      <Point X="244.0" Y="218.21309523809524" T="1650653648"/>
      <Point X="244.0" Y="220.42619047619047" T="1650653648"/>
      <Point X="244.0" Y="222.6392857142857" T="1650653648"/>
      <Point X="244.0" Y="223.0" T="1650653648"/>
      <Point X="244.0" Y="224.85238095238094" T="1650653648"/>
      <Point X="244.0" Y="227.06547619047618" T="1650653648"/>
      <Point X="244.0" Y="229.2785714285714" T="1650653648"/>
      <Point X="244.0" Y="231.49166666666665" T="1650653648"/>
      <Point X="244.0" Y="233.70476190476188" T="1650653648"/>
      <Point X="244.0" Y="235.91785714285712" T="1650653648"/>
      <Point X="244.0" Y="238.13095238095235" T="1650653648"/>
      <Point X="244.0" Y="240.0" T="1650653648"/>
      <Point X="244.0" Y="240.3440476190476" T="1650653648"/>
      <Point X="244.0" Y="242.55714285714282" T="1650653648"/>
      <Point X="244.0" Y="244.77023809523806" T="1650653648"/>
      <Point X="244.0" Y="246.9833333333333" T="1650653648"/>
      <Point X="244.0" Y="249.19642857142853" T="1650653648"/>
      <Point X="244.0" Y="251.40952380952376" T="1650653648"/>
      <Point X="244.0" Y="253.622619047619" T="1650653648"/>
      <Point X="244.0" Y="255.83571428571423" T="1650653648"/>
      <Point X="244.0" Y="258.0488095238095" T="1650653648"/>
      <Point X="244.0" Y="260.26190476190476" T="1650653648"/>
      <Point X="244.0" Y="262.475" T="1650653648"/>
      <Point X="244.0" Y="264.6880952380953" T="1650653648"/>
      <Point X="244.0" Y="266.90119047619055" T="1650653648"/>
      <Point X="244.0" Y="269.1142857142858" T="1650653648"/>
      <Point X="244.0" Y="270.0" T="1650653648"/>
      <Point X="244.0" Y="271.3273809523811" T="1650653648"/>
      <Point X="244.0" Y="273.54047619047634" T="1650653648"/>
      <Point X="244.0" Y="275.7535714285716" T="1650653648"/>
      <Point X="244.0" Y="277.96666666666687" T="1650653648"/>
      <Point X="244.0" Y="280.17976190476213" T="1650653648"/>
      <Point X="244.0" Y="282.3928571428574" T="1650653648"/>
      <Point X="244.0" Y="284.60595238095266" T="1650653648"/>
      <Point X="244.0" Y="286.8190476190479" T="1650653648"/>
      <Point X="244.0" Y="289.0" T="1650653648"/>
      <Point X="244.0" Y="289.0321428571432" T="1650653648"/>
      <Point X="244.0" Y="291.24523809523845" T="1650653648"/>
      <Point X="244.0" Y="293.4583333333337" T="1650653648"/>
      <Point X="244.0" Y="295.671428571429" T="1650653648"/>
      <Point X="244.0" Y="297.88452380952424" T="1650653648"/>
      <Point X="244.0" Y="300.0976190476195" T="1650653648"/>
      <Point X="244.0" Y="302.31071428571477" T="1650653648"/>
      <Point X="244.0" Y="304.52380952381003" T="1650653648"/>
      <Point X="244.0" Y="306.7369047619053" T="1650653648"/>
      <Point X="244.0" Y="308.95000000000056" T="1650653648"/>
      <Point X="244.0" Y="311.1630952380958" T="1650653648"/>
      <Point X="244.0" Y="312.0" T="1650653648"/>
      <Point X="244.0" Y="313.3761904761911" T="1650653648"/>
      <Point X="244.0" Y="315.58928571428635" T="1650653648"/>
      <Point X="244.0" Y="317.8023809523816" T="1650653648"/>
      <Point X="244.0" Y="320.0154761904769" T="1650653648"/>
      <Point X="244.0" Y="322.22857142857214" T="1650653648"/>
      <Point X="244.0" Y="324.4416666666674" T="1650653648"/>
      <Point X="244.0" Y="326.65476190476267" T="1650653648"/>
      <Point X="244.0" Y="328.86785714285793" T="1650653648"/>
      <Point X="244.0" Y="331.0809523809532" T="1650653648"/>
      <Point X="244.0" Y="332.0" T="1650653648"/>
      <Point X="244.0" Y="333.29404761904846" T="1650653648"/>
      <Point X="244.0" Y="335.5071428571437" T="1650653648"/>
      <Point X="244.0" Y="337.720238095239" T="1650653648"/>
      <Point X="244.0" Y="339.93333333333425" T="1650653648"/>
      <Point X="244.0" Y="342.1464285714295" T="1650653648"/>
      <Point X="244.0" Y="344.0" T="1650653648"/>
      <Point X="244.0" Y="344.3595238095248" T="1650653648"/>
      <Point X="244.0" Y="346.57261904762004" T="1650653648"/>
      <Point X="244.0" Y="348.7857142857153" T="1650653648"/>
      <Point X="244.0" Y="350.99880952381056" T="1650653648"/>
      <Point X="244.0" Y="353.2119047619058" T="1650653648"/>
      <Point X="244.0" Y="355.0" T="1650653648"/>
      <Point X="244.0" Y="355.4250000000011" T="1650653648"/>
      <Point X="244.0" Y="357.63809523809635" T="1650653648"/>
      <Point X="244.0" Y="358.0" T="1650653648"/>
      <Point X="244.0" Y="359.0" T="1650653648"/>
    </Stroke>
    <Stroke>
      <Point X="203.0" Y="237.0" T="1650653648"/>
      <Point X="203.0" Y="236.0" T="1650653648"/>
      <Point X="203.0" Y="237.0" T="1650653648"/>
      <Point X="203.0" Y="237.98597679265032" T="1650653648"/>
      <Point X="203.0" Y="240.97195358530064" T="1650653648"/>
      <Point X="203.0" Y="242.0" T="1650653648"/>
      <Point X="203.0" Y="243.95793037795096" T="1650653648"/>
      <Point X="203.0" Y="246.94390717060128" T="1650653648"/>
      <Point X="203.0" Y="249.9298839632516" T="1650653648"/>
      <Point X="203.0" Y="252.0" T="1650653648"/>
      <Point X="203.10113990094632" Y="252.91025910851678" T="1650653648"/>
      <Point X="203.43088587498278" Y="255.87797287484483" T="1650653648"/>
      <Point X="203.7606318490192" Y="258.84568664117285" T="1650653648"/>
      <Point X="204.0" Y="261.0" T="1650653648"/>
      <Point X="204.30394835628098" Y="261.7598708907025" T="1650653648"/>
      <Point X="205.41291229688105" Y="264.5322807422026" T="1650653648"/>
      <Point X="206.0" Y="266.0" T="1650653648"/>
      <Point X="206.5535333396945" Y="267.2915777926205" T="1650653648"/>
      <Point X="207.72976722342898" Y="270.0361235213343" T="1650653648"/>
      <Point X="208.90600110716346" Y="272.78066925004805" T="1650653648"/>
      <Point X="209.0" Y="273.0" T="1650653648"/>
      <Point X="210.716257217005" Y="275.1453215212563" T="1650653648"/>
      <Point X="212.5815821314861" Y="277.4769776643576" T="1650653648"/>
      <Point X="213.0" Y="278.0" T="1650653648"/>
      <Point X="214.85294511506896" Y="279.38970883630174" T="1650653648"/>
      <Point X="217.0" Y="281.0" T="1650653648"/>
      <Point X="217.27025849797676" Y="281.1351292489884" T="1650653648"/>
      <Point X="219.94099733301792" Y="282.47049866650895" T="1650653648"/>
      <Point X="222.61173616805905" Y="283.80586808402956" T="1650653648"/>
      <Point X="223.0" Y="284.0" T="1650653648"/>
      <Point X="225.53217866419774" Y="284.3165223330247" T="1650653648"/>
      <Point X="228.49509737592507" Y="284.68688717199063" T="1650653648"/>
      <Point X="231.0" Y="285.0" T="1650653648"/>
      <Point X="231.45530016992214" Y="285.07588336165367" T="1650653648"/>
      <Point X="234.4006495348962" Y="285.5667749224827" T="1650653648"/>
      <Point X="237.0" Y="286.0" T="1650653648"/>
      <Point X="237.3507715239425" Y="286.0" T="1650653648"/>
      <Point X="240.33674831659283" Y="286.0" T="1650653648"/>
      <Point X="243.32272510924315" Y="286.0" T="1650653648"/>
      <Point X="246.30870190189347" Y="286.0" T="1650653648"/>
      <Point X="247.0" Y="286.0" T="1650653648"/>
      <Point X="249.2946786945438" Y="286.0" T="1650653648"/>
      <Point X="252.2806554871941" Y="286.0" T="1650653648"/>
      <Point X="255.0" Y="286.0" T="1650653648"/>
      <Point X="255.26663227984443" Y="286.0" T="1650653648"/>
      <Point X="258.25260907249475" Y="286.0" T="1650653648"/>
      <Point X="261.23858586514507" Y="286.0" T="1650653648"/>
      <Point X="262.0" Y="286.0" T="1650653648"/>
      <Point X="264.2245626577954" Y="286.0" T="1650653648"/>
      <Point X="267.0" Y="286.0" T="1650653648"/>
      <Point X="267.20425326883463" Y="285.9489366827913" T="1650653648"/>
      <Point X="270.1010762598323" Y="285.2247309350419" T="1650653648"/>
      <Point X="271.0" Y="285.0" T="1650653648"/>
      <Point X="272.99789925083" Y="284.5005251872925" T="1650653648"/>
      <Point X="275.0" Y="284.0" T="1650653648"/>
      <Point X="275.87493130863675" Y="283.7083562304544" T="1650653648"/>
      <Point X="278.0" Y="283.0" T="1650653648"/>
      <Point X="278.5967661677146" Y="282.55242537421407" T="1650653648"/>
      <Point X="280.9855476018348" Y="280.76083929862386" T="1650653648"/>
      <Point X="282.0" Y="280.0" T="1650653648"/>
      <Point X="283.21474672613175" Y="278.78525327386825" T="1650653648"/>
      <Point X="285.3261511646804" Y="276.6738488353196" T="1650653648"/>
      <Point X="286.0" Y="276.0" T="1650653648"/>
      <Point X="287.5618020281914" Y="274.6984983098405" T="1650653648"/>
      <Point X="289.85569294068927" Y="272.7869225494256" T="1650653648"/>
      <Point X="292.0" Y="271.0" T="1650653648"/>
      <Point X="292.1001798044251" Y="270.83303365929146" T="1650653648"/>
      <Point X="293.63645219004883" Y="268.272579683252" T="1650653648"/>
      <Point X="295.0" Y="266.0" T="1650653648"/>
      <Point X="295.1862218589905" Y="265.7206672115142" T="1650653648"/>
      <Point X="296.84254377179764" Y="263.23618434230355" T="1650653648"/>
      <Point X="298.49886568460477" Y="260.7517014730929" T="1650653648"/>
      <Point X="299.0" Y="260.0" T="1650653648"/>
      <Point X="299.7734374460983" Y="258.0664063847543" T="1650653648"/>
      <Point X="300.88240138669835" Y="255.2939965332542" T="1650653648"/>
      <Point X="301.0" Y="255.0" T="1650653648"/>
      <Point X="301.0" Y="252.33066716420967" T="1650653648"/>
      <Point X="301.0" Y="251.0" T="1650653648"/>
      <Point X="301.0" Y="249.34469037155935" T="1650653648"/>
      <Point X="301.0" Y="246.35871357890903" T="1650653648"/>
      <Point X="301.0" Y="246.0" T="1650653648"/>
      <Point X="301.0" Y="243.3727367862587" T="1650653648"/>
      <Point X="301.0" Y="240.3867599936084" T="1650653648"/>
      <Point X="301.0" Y="239.0" T="1650653648"/>
      <Point X="301.0" Y="237.40078320095807" T="1650653648"/>
      <Point X="301.0" Y="234.41480640830775" T="1650653648"/>
      <Point X="301.0" Y="231.42882961565743" T="1650653648"/>
      <Point X="301.0" Y="230.0" T="1650653648"/>
      <Point X="301.0" Y="228.44285282300712" T="1650653648"/>
      <Point X="301.0" Y="225.4568760303568" T="1650653648"/>
      <Point X="301.0" Y="224.0" T="1650653648"/>
      <Point X="301.0" Y="222.47089923770648" T="1650653648"/>
      <Point X="301.0" Y="219.48492244505616" T="1650653648"/>
      <Point X="301.0" Y="219.0" T="1650653648"/>
      <Point X="300.2090971709736" Y="216.6272915129208" T="1650653648"/>
      <Point X="300.0" Y="216.0" T="1650653648"/>
      <Point X="299.26484840045566" Y="213.79454520136701" T="1650653648"/>
      <Point X="299.0" Y="213.0" T="1650653648"/>
      <Point X="298.0" Y="213.0" T="1650653648"/>
    </Stroke>
  </Gesture>
