<?xml version="1.0" ?>
  <Gesture Name="X05" Subject="3" Speed="medium" Number="5" NumPts="175" AppName="dollarstore-notepad" Date="2022-04-22" Time="1650653648">
    <Stroke>
      <Point X="179.0" Y="228.0" T="1650653648"/>
      <Point X="181.0" Y="228.0" T="1650653648"/>
      <Point X="181.2075600774285" Y="228.06918669247617" T="1650653648"/>
      <Point X="183.31248675095802" Y="228.770828916986" T="1650653648"/>
      <Point X="184.0" Y="229.0" T="1650653648"/>
      <Point X="185.3116505507202" Y="229.7154457549383" T="1650653648"/>
      <Point X="187.25951430229915" Y="230.77791689216318" T="1650653648"/>
      <Point X="189.2073780538781" Y="231.84038802938807" T="1650653648"/>
      <Point X="191.15524180545705" Y="232.90285916661296" T="1650653648"/>
      <Point X="193.103105557036" Y="233.96533030383782" T="1650653648"/>
      <Point X="195.0" Y="235.0" T="1650653648"/>
      <Point X="195.05111883987465" Y="235.02752552916328" T="1650653648"/>
      <Point X="197.0046971386668" Y="236.07945230543598" T="1650653648"/>
      <Point X="198.95827543745898" Y="237.13137908170867" T="1650653648"/>
      <Point X="200.91185373625115" Y="238.18330585798137" T="1650653648"/>
      <Point X="202.8654320350433" Y="239.23523263425406" T="1650653648"/>
      <Point X="204.81901033383548" Y="240.28715941052675" T="1650653648"/>
      <Point X="206.77258863262765" Y="241.33908618679945" T="1650653648"/>
      <Point X="208.7261669314198" Y="242.39101296307214" T="1650653648"/>
      <Point X="210.67974523021198" Y="243.44293973934487" T="1650653648"/>
      <Point X="212.63332352900414" Y="244.4948665156176" T="1650653648"/>
      <Point X="214.5869018277963" Y="245.54679329189028" T="1650653648"/>
      <Point X="216.54048012658848" Y="246.598720068163" T="1650653648"/>
      <Point X="218.49405842538064" Y="247.65064684443573" T="1650653648"/>
      <Point X="220.4476367241728" Y="248.70257362070842" T="1650653648"/>
      <Point X="221.0" Y="249.0" T="1650653648"/>
      <Point X="222.36464668709831" Y="249.81878801225898" T="1650653648"/>
      <Point X="224.26724129944606" Y="250.96034477966762" T="1650653648"/>
      <Point X="226.0" Y="252.0" T="1650653648"/>
      <Point X="226.16918342553691" Y="252.10298121554422" T="1650653648"/>
      <Point X="228.0644685305852" Y="253.2566330186171" T="1650653648"/>
      <Point X="229.9597536356335" Y="254.41028482168997" T="1650653648"/>
      <Point X="231.85503874068178" Y="255.56393662476285" T="1650653648"/>
      <Point X="233.75032384573007" Y="256.7175884278357" T="1650653648"/>
      <Point X="235.64560895077835" Y="257.8712402309086" T="1650653648"/>
      <Point X="237.54089405582664" Y="259.0248920339815" T="1650653648"/>
      <Point X="239.43617916087493" Y="260.17854383705435" T="1650653648"/>
      <Point X="241.33146426592322" Y="261.3321956401272" T="1650653648"/>
      <Point X="243.2267493709715" Y="262.4858474432001" T="1650653648"/>
      <Point X="245.1220344760198" Y="263.639499246273" T="1650653648"/>
      <Point X="247.01731958106808" Y="264.7931510493458" T="1650653648"/>
      <Point X="248.91260468611637" Y="265.94680285241867" T="1650653648"/>
      <Point X="249.0" Y="266.0" T="1650653648"/>
      <Point X="250.78558835161286" Y="267.1362834964809" T="1650653648"/>
      <Point X="252.65749394182" Y="268.32749614479457" T="1650653648"/>
      <Point X="254.52939953202716" Y="269.5187087931082" T="1650653648"/>
      <Point X="256.4013051222343" Y="270.70992144142184" T="1650653648"/>
      <Point X="258.2732107124414" Y="271.9011340897355" T="1650653648"/>
      <Point X="260.14511630264855" Y="273.0923467380491" T="1650653648"/>
      <Point X="262.0170218928557" Y="274.28355938636275" T="1650653648"/>
      <Point X="263.88892748306284" Y="275.4747720346764" T="1650653648"/>
      <Point X="265.76083307327" Y="276.66598468299003" T="1650653648"/>
      <Point X="267.63273866347714" Y="277.85719733130367" T="1650653648"/>
      <Point X="269.5046442536843" Y="279.0484099796173" T="1650653648"/>
      <Point X="271.0" Y="280.0" T="1650653648"/>
      <Point X="271.3428787577872" Y="280.285732298156" T="1650653648"/>
      <Point X="273.0473985547737" Y="281.7061654623114" T="1650653648"/>
      <Point X="274.75191835176014" Y="283.1265986264668" T="1650653648"/>
      <Point X="276.4564381487466" Y="284.54703179062216" T="1650653648"/>
      <Point X="278.16095794573306" Y="285.96746495477754" T="1650653648"/>
      <Point X="279.8654777427195" Y="287.3878981189329" T="1650653648"/>
      <Point X="281.569997539706" Y="288.8083312830883" T="1650653648"/>
      <Point X="283.0" Y="290.0" T="1650653648"/>
      <Point X="283.29274555512467" Y="290.20492188858725" T="1650653648"/>
      <Point X="285.11044712618735" Y="291.4773129883311" T="1650653648"/>
      <Point X="286.92814869725004" Y="292.74970408807496" T="1650653648"/>
      <Point X="288.7458502683127" Y="294.0220951878189" T="1650653648"/>
      <Point X="290.5635518393754" Y="295.29448628756273" T="1650653648"/>
      <Point X="292.3812534104381" Y="296.56687738730665" T="1650653648"/>
      <Point X="293.0" Y="297.0" T="1650653648"/>
      <Point X="294.0348585992834" Y="298.0348585992834" T="1650653648"/>
      <Point X="295.60377830917156" Y="299.60377830917156" T="1650653648"/>
      <Point X="297.0" Y="301.0" T="1650653648"/>
      <Point X="297.17269801905974" Y="301.17269801905974" T="1650653648"/>
      <Point X="298.7416177289479" Y="302.7416177289479" T="1650653648"/>
      <Point X="299.0" Y="303.0" T="1650653648"/>
      <Point X="300.0" Y="303.0" T="1650653648"/>
    </Stroke>
    <Stroke>
      <Point X="283.0" Y="201.0" T="1650653648"/>
      <Point X="281.29473683465403" Y="202.70526316534597" T="1650653648"/>
      <Point X="279.58947366930806" Y="204.41052633069194" T="1650653648"/>
      <Point X="279.0" Y="205.0" T="1650653648"/>
      <Point X="277.8842105039621" Y="206.1157894960379" T="1650653648"/>
      <Point X="276.1789473386161" Y="207.82105266138387" T="1650653648"/>
      <Point X="274.47368417327016" Y="209.52631582672984" T="1650653648"/>
      <Point X="273.0" Y="211.0" T="1650653648"/>
      <Point X="272.7796982128087" Y="211.24233196591044" T="1650653648"/>
      <Point X="271.1574762677618" Y="213.02677610546198" T="1650653648"/>
      <Point X="269.53525432271493" Y="214.81122024501352" T="1650653648"/>
      <Point X="267.91303237766806" Y="216.59566438456505" T="1650653648"/>
      <Point X="266.2908104326212" Y="218.3801085241166" T="1650653648"/>
      <Point X="264.6685884875743" Y="220.16455266366816" T="1650653648"/>
      <Point X="263.04636654252744" Y="221.94899680321973" T="1650653648"/>
      <Point X="261.42414459748056" Y="223.7334409427713" T="1650653648"/>
      <Point X="259.8019226524337" Y="225.51788508232286" T="1650653648"/>
      <Point X="258.1797007073868" Y="227.30232922187443" T="1650653648"/>
      <Point X="256.55747876233994" Y="229.086773361426" T="1650653648"/>
      <Point X="254.9352568172931" Y="230.87121750097756" T="1650653648"/>
      <Point X="253.31303487224625" Y="232.65566164052913" T="1650653648"/>
      <Point X="253.0" Y="233.0" T="1650653648"/>
      <Point X="251.7278946132205" Y="234.47296413206047" T="1650653648"/>
      <Point X="250.15162081880283" Y="236.29812326243885" T="1650653648"/>
      <Point X="248.57534702438514" Y="238.12328239281723" T="1650653648"/>
      <Point X="246.99907322996745" Y="239.9484415231956" T="1650653648"/>
      <Point X="245.42279943554976" Y="241.773600653574" T="1650653648"/>
      <Point X="243.84652564113208" Y="243.59875978395237" T="1650653648"/>
      <Point X="242.2702518467144" Y="245.42391891433076" T="1650653648"/>
      <Point X="240.6939780522967" Y="247.24907804470914" T="1650653648"/>
      <Point X="239.117704257879" Y="249.07423717508752" T="1650653648"/>
      <Point X="237.54143046346132" Y="250.8993963054659" T="1650653648"/>
      <Point X="235.9651566690436" Y="252.72455543584425" T="1650653648"/>
      <Point X="234.38888287462592" Y="254.54971456622263" T="1650653648"/>
      <Point X="234.0" Y="255.0" T="1650653648"/>
      <Point X="232.48846552999728" Y="256.0076896466685" T="1650653648"/>
      <Point X="231.0" Y="257.0" T="1650653648"/>
      <Point X="230.6110065382446" Y="257.48624182719425" T="1650653648"/>
      <Point X="229.10448802857758" Y="259.369389964278" T="1650653648"/>
      <Point X="227.59796951891056" Y="261.2525381013618" T="1650653648"/>
      <Point X="227.0" Y="262.0" T="1650653648"/>
      <Point X="226.1273671904588" Y="263.16351041272156" T="1650653648"/>
      <Point X="224.68040341295028" Y="265.0927954493996" T="1650653648"/>
      <Point X="224.0" Y="266.0" T="1650653648"/>
      <Point X="223.42863963866358" Y="267.14272072267283" T="1650653648"/>
      <Point X="223.0" Y="268.0" T="1650653648"/>
      <Point X="222.0" Y="269.0" T="1650653648"/>
      <Point X="221.98769071923633" Y="269.03692784229105" T="1650653648"/>
      <Point X="221.2250738477883" Y="271.3247784566351" T="1650653648"/>
      <Point X="221.0" Y="272.0" T="1650653648"/>
      <Point X="219.7980172582661" Y="273.2019827417339" T="1650653648"/>
      <Point X="219.0" Y="274.0" T="1650653648"/>
      <Point X="218.09275409292013" Y="274.90724590707987" T="1650653648"/>
      <Point X="218.0" Y="275.0" T="1650653648"/>
      <Point X="217.0" Y="277.0" T="1650653648"/>
      <Point X="217.0" Y="277.04436422217447" T="1650653648"/>
      <Point X="217.0" Y="278.0" T="1650653648"/>
      <Point X="217.0" Y="279.0" T="1650653648"/>
      <Point X="217.0" Y="279.455970518022" T="1650653648"/>
      <Point X="217.0" Y="281.86757681386956" T="1650653648"/>
      <Point X="217.0" Y="283.0" T="1650653648"/>
      <Point X="216.4279319222006" Y="284.1441361555988" T="1650653648"/>
      <Point X="215.3494287997043" Y="286.3011424005914" T="1650653648"/>
      <Point X="215.0" Y="287.0" T="1650653648"/>
      <Point X="214.270925677208" Y="288.458148645584" T="1650653648"/>
      <Point X="213.1924225547117" Y="290.6151548905766" T="1650653648"/>
      <Point X="213.0" Y="291.0" T="1650653648"/>
      <Point X="212.37344642184186" Y="292.8796607344744" T="1650653648"/>
      <Point X="212.0" Y="294.0" T="1650653648"/>
      <Point X="211.1297884198465" Y="294.87021158015347" T="1650653648"/>
      <Point X="211.0" Y="295.0" T="1650653648"/>
      <Point X="210.0" Y="296.0" T="1650653648"/>
      <Point X="209.3228407022581" Y="296.45143953182793" T="1650653648"/>
      <Point X="207.31626297397116" Y="297.7891580173526" T="1650653648"/>
      <Point X="207.0" Y="298.0" T="1650653648"/>
      <Point X="205.18296623666055" Y="298.9085168816697" T="1650653648"/>
      <Point X="205.0" Y="299.0" T="1650653648"/>
      <Point X="202.95081125321977" Y="299.8196754987121" T="1650653648"/>
      <Point X="200.71169101993317" Y="300.7153235920267" T="1650653648"/>
      <Point X="200.0" Y="301.0" T="1650653648"/>
      <Point X="198.63120104249555" Y="301.9125326383363" T="1650653648"/>
      <Point X="197.0" Y="303.0" T="1650653648"/>
      <Point X="196.54885337058846" Y="303.0" T="1650653648"/>
      <Point X="195.0" Y="303.0" T="1650653648"/>
      <Point X="194.22833032453357" Y="303.3858348377332" T="1650653648"/>
      <Point X="193.0" Y="304.0" T="1650653648"/>
      <Point X="192.0149904386781" Y="304.32833652044064" T="1650653648"/>
      <Point X="190.0" Y="305.0" T="1650653648"/>
      <Point X="189.76068579478266" Y="305.15954280347825" T="1650653648"/>
      <Point X="187.75410806649572" Y="306.4972612890029" T="1650653648"/>
      <Point X="187.0" Y="307.0" T="1650653648"/>
      <Point X="185.5719648709434" Y="307.4760117096855" T="1650653648"/>
      <Point X="184.0" Y="308.0" T="1650653648"/>
      <Point X="183.32505644838218" Y="308.3374717758089" T="1650653648"/>
      <Point X="182.0" Y="309.0" T="1650653648"/>
      <Point X="181.3422859359493" Y="309.6577140640507" T="1650653648"/>
      <Point X="181.0" Y="310.0" T="1650653648"/>
      <Point X="181.0" Y="309.0" T="1650653648"/>
    </Stroke>
  </Gesture>
