<?xml version="1.0" ?>
  <Gesture Name="P05" Subject="2" Speed="medium" Number="5" NumPts="177" AppName="dollarstore-notepad" Date="2022-04-22" Time="1650653648">
    <Stroke>
      <Point X="199.0" Y="116.0" T="1650653648"/>
      <Point X="199.0" Y="117.0" T="1650653648"/>
      <Point X="199.0" Y="118.15119047619048" T="1650653648"/>
      <Point X="199.0" Y="119.0" T="1650653648"/>
      <Point X="199.0" Y="120.30238095238096" T="1650653648"/>
      <Point X="199.0" Y="122.45357142857144" T="1650653648"/>
      <Point X="199.0" Y="124.60476190476192" T="1650653648"/>
      <Point X="199.0" Y="126.0" T="1650653648"/>
      <Point X="199.0" Y="126.7559523809524" T="1650653648"/>
      <Point X="199.0" Y="128.90714285714287" T="1650653648"/>
      <Point X="199.0" Y="131.05833333333334" T="1650653648"/>
      <Point X="199.0" Y="133.2095238095238" T="1650653648"/>
      <Point X="199.0" Y="135.36071428571427" T="1650653648"/>
      <Point X="199.0" Y="137.51190476190473" T="1650653648"/>
      <Point X="199.0" Y="139.6630952380952" T="1650653648"/>
      <Point X="199.0" Y="141.81428571428566" T="1650653648"/>
      <Point X="199.0" Y="143.96547619047612" T="1650653648"/>
      <Point X="199.0" Y="146.1166666666666" T="1650653648"/>
      <Point X="199.0" Y="147.0" T="1650653648"/>
      <Point X="199.0" Y="148.26785714285705" T="1650653648"/>
      <Point X="199.0" Y="150.41904761904752" T="1650653648"/>
      <Point X="199.0" Y="152.57023809523798" T="1650653648"/>
      <Point X="199.0" Y="154.72142857142845" T="1650653648"/>
      <Point X="199.0" Y="156.8726190476189" T="1650653648"/>
      <Point X="199.0" Y="159.02380952380938" T="1650653648"/>
      <Point X="199.0" Y="161.17499999999984" T="1650653648"/>
      <Point X="199.0" Y="163.3261904761903" T="1650653648"/>
      <Point X="199.0" Y="165.0" T="1650653648"/>
      <Point X="199.0" Y="165.47738095238077" T="1650653648"/>
      <Point X="199.0" Y="167.62857142857123" T="1650653648"/>
      <Point X="199.0" Y="169.7797619047617" T="1650653648"/>
      <Point X="199.0" Y="171.93095238095216" T="1650653648"/>
      <Point X="199.0" Y="174.08214285714263" T="1650653648"/>
      <Point X="199.0" Y="176.2333333333331" T="1650653648"/>
      <Point X="199.0" Y="178.38452380952356" T="1650653648"/>
      <Point X="199.0" Y="180.53571428571402" T="1650653648"/>
      <Point X="199.0" Y="182.6869047619045" T="1650653648"/>
      <Point X="199.0" Y="184.83809523809495" T="1650653648"/>
      <Point X="199.0" Y="186.98928571428542" T="1650653648"/>
      <Point X="199.0" Y="189.14047619047588" T="1650653648"/>
      <Point X="199.0" Y="191.29166666666634" T="1650653648"/>
      <Point X="199.0" Y="193.0" T="1650653648"/>
      <Point X="199.0" Y="193.4428571428568" T="1650653648"/>
      <Point X="199.0" Y="195.59404761904727" T="1650653648"/>
      <Point X="199.0" Y="197.74523809523774" T="1650653648"/>
      <Point X="199.0" Y="199.8964285714282" T="1650653648"/>
      <Point X="199.0" Y="202.04761904761867" T="1650653648"/>
      <Point X="199.0" Y="204.19880952380913" T="1650653648"/>
      <Point X="199.0" Y="206.3499999999996" T="1650653648"/>
      <Point X="199.0" Y="208.50119047619006" T="1650653648"/>
      <Point X="199.0" Y="210.65238095238053" T="1650653648"/>
      <Point X="199.0" Y="212.803571428571" T="1650653648"/>
      <Point X="199.0" Y="214.95476190476145" T="1650653648"/>
      <Point X="199.0" Y="217.0" T="1650653648"/>
      <Point X="199.0" Y="217.10595238095192" T="1650653648"/>
      <Point X="199.0" Y="219.25714285714238" T="1650653648"/>
      <Point X="199.0" Y="221.40833333333285" T="1650653648"/>
      <Point X="199.0" Y="223.5595238095233" T="1650653648"/>
      <Point X="199.0" Y="225.71071428571378" T="1650653648"/>
      <Point X="199.0" Y="227.86190476190424" T="1650653648"/>
      <Point X="199.0" Y="230.0130952380947" T="1650653648"/>
      <Point X="199.0" Y="232.16428571428517" T="1650653648"/>
      <Point X="199.0" Y="234.0" T="1650653648"/>
      <Point X="199.0" Y="234.31547619047564" T="1650653648"/>
      <Point X="199.0" Y="236.4666666666661" T="1650653648"/>
      <Point X="199.0" Y="238.61785714285656" T="1650653648"/>
      <Point X="199.0" Y="240.76904761904703" T="1650653648"/>
      <Point X="199.0" Y="242.9202380952375" T="1650653648"/>
      <Point X="199.0" Y="244.0" T="1650653648"/>
      <Point X="199.0" Y="245.07142857142796" T="1650653648"/>
      <Point X="199.0" Y="247.22261904761842" T="1650653648"/>
      <Point X="199.0" Y="249.3738095238089" T="1650653648"/>
      <Point X="199.0" Y="251.0" T="1650653648"/>
      <Point X="199.0" Y="251.52499999999935" T="1650653648"/>
      <Point X="199.0" Y="253.67619047618982" T="1650653648"/>
      <Point X="199.0" Y="255.0" T="1650653648"/>
    </Stroke>
    <Stroke>
      <Point X="200.0" Y="127.0" T="1650653648"/>
      <Point X="202.0" Y="127.0" T="1650653648"/>
      <Point X="202.7934166109457" Y="127.0" T="1650653648"/>
      <Point X="204.0" Y="127.0" T="1650653648"/>
      <Point X="205.0" Y="127.0" T="1650653648"/>
      <Point X="205.58683322189142" Y="127.0" T="1650653648"/>
      <Point X="208.38024983283714" Y="127.0" T="1650653648"/>
      <Point X="211.0" Y="127.0" T="1650653648"/>
      <Point X="211.17366644378285" Y="127.0" T="1650653648"/>
      <Point X="213.96708305472856" Y="127.0" T="1650653648"/>
      <Point X="216.0" Y="127.0" T="1650653648"/>
      <Point X="216.76049966567427" Y="127.0" T="1650653648"/>
      <Point X="219.55391627662" Y="127.0" T="1650653648"/>
      <Point X="221.0" Y="127.0" T="1650653648"/>
      <Point X="222.3473328875657" Y="127.0" T="1650653648"/>
      <Point X="225.1407494985114" Y="127.0" T="1650653648"/>
      <Point X="227.0" Y="127.0" T="1650653648"/>
      <Point X="227.93416610945712" Y="127.0" T="1650653648"/>
      <Point X="230.72758272040284" Y="127.0" T="1650653648"/>
      <Point X="233.52099933134855" Y="127.0" T="1650653648"/>
      <Point X="236.0" Y="127.0" T="1650653648"/>
      <Point X="236.31125590287323" Y="127.04446512898188" T="1650653648"/>
      <Point X="239.07659726246365" Y="127.43951389463766" T="1650653648"/>
      <Point X="241.84193862205407" Y="127.83456266029343" T="1650653648"/>
      <Point X="243.0" Y="128.0" T="1650653648"/>
      <Point X="244.52022214564764" Y="128.57008330461787" T="1650653648"/>
      <Point X="247.13577962358215" Y="129.55091735884332" T="1650653648"/>
      <Point X="249.75133710151667" Y="130.53175141306875" T="1650653648"/>
      <Point X="251.0" Y="131.0" T="1650653648"/>
      <Point X="252.25180594619223" Y="131.75108356771534" T="1650653648"/>
      <Point X="254.6471409286461" Y="133.18828455718767" T="1650653648"/>
      <Point X="256.0" Y="134.0" T="1650653648"/>
      <Point X="256.9493220283972" Y="134.75945762271775" T="1650653648"/>
      <Point X="259.13061393166475" Y="136.5044911453318" T="1650653648"/>
      <Point X="261.0" Y="138.0" T="1650653648"/>
      <Point X="261.1786324773261" Y="138.35726495465224" T="1650653648"/>
      <Point X="262.42788636363645" Y="140.85577272727292" T="1650653648"/>
      <Point X="263.6771402499468" Y="143.3542804998936" T="1650653648"/>
      <Point X="264.92639413625716" Y="145.8527882725143" T="1650653648"/>
      <Point X="266.0" Y="148.0" T="1650653648"/>
      <Point X="266.1547161055541" Y="148.3610042462929" T="1650653648"/>
      <Point X="267.2550968175772" Y="150.92855924101355" T="1650653648"/>
      <Point X="268.35547752960036" Y="153.49611423573418" T="1650653648"/>
      <Point X="269.0" Y="155.0" T="1650653648"/>
      <Point X="269.2269529744812" Y="156.13476487240598" T="1650653648"/>
      <Point X="269.7747870440507" Y="158.87393522025337" T="1650653648"/>
      <Point X="270.0" Y="160.0" T="1650653648"/>
      <Point X="270.23264539354096" Y="161.62851775478666" T="1650653648"/>
      <Point X="270.6276941591967" Y="164.39385911437708" T="1650653648"/>
      <Point X="271.0" Y="167.0" T="1650653648"/>
      <Point X="271.0" Y="167.1608167638722" T="1650653648"/>
      <Point X="271.0" Y="169.9542333748179" T="1650653648"/>
      <Point X="271.0" Y="172.0" T="1650653648"/>
      <Point X="271.0" Y="172.74764998576362" T="1650653648"/>
      <Point X="271.0" Y="175.0" T="1650653648"/>
      <Point X="270.6998702526344" Y="175.45019462104838" T="1650653648"/>
      <Point X="269.150361510404" Y="177.774457734394" T="1650653648"/>
      <Point X="269.0" Y="178.0" T="1650653648"/>
      <Point X="267.6008527681736" Y="180.0987208477396" T="1650653648"/>
      <Point X="267.0" Y="181.0" T="1650653648"/>
      <Point X="265.5770160389148" Y="181.9486559740568" T="1650653648"/>
      <Point X="264.0" Y="183.0" T="1650653648"/>
      <Point X="263.1745349537972" Y="183.3537707340869" T="1650653648"/>
      <Point X="260.60697995907657" Y="184.45415144611005" T="1650653648"/>
      <Point X="258.03942496435593" Y="185.55453215813318" T="1650653648"/>
      <Point X="257.0" Y="186.0" T="1650653648"/>
      <Point X="255.5129647597454" Y="186.7435176201273" T="1650653648"/>
      <Point X="255.0" Y="187.0" T="1650653648"/>
      <Point X="252.89401360688746" Y="187.70199546437084" T="1650653648"/>
      <Point X="250.24394592358638" Y="188.58535135880453" T="1650653648"/>
      <Point X="247.5938782402853" Y="189.46870725323822" T="1650653648"/>
      <Point X="246.0" Y="190.0" T="1650653648"/>
      <Point X="244.91991956748893" Y="190.27002010812777" T="1650653648"/>
      <Point X="242.20990739259855" Y="190.94752315185036" T="1650653648"/>
      <Point X="239.49989521770817" Y="191.62502619557296" T="1650653648"/>
      <Point X="238.0" Y="192.0" T="1650653648"/>
      <Point X="236.7526399915467" Y="192.0" T="1650653648"/>
      <Point X="233.95922338060097" Y="192.0" T="1650653648"/>
      <Point X="231.16580676965526" Y="192.0" T="1650653648"/>
      <Point X="230.0" Y="192.0" T="1650653648"/>
      <Point X="228.4039972420662" Y="192.31920055158676" T="1650653648"/>
      <Point X="225.6648268942188" Y="192.86703462115625" T="1650653648"/>
      <Point X="225.0" Y="193.0" T="1650653648"/>
      <Point X="222.91335906435387" Y="193.34777348927435" T="1650653648"/>
      <Point X="220.15794989258524" Y="193.8070083512358" T="1650653648"/>
      <Point X="219.0" Y="194.0" T="1650653648"/>
      <Point X="217.41195524270387" Y="194.31760895145922" T="1650653648"/>
      <Point X="214.67278489485648" Y="194.8654430210287" T="1650653648"/>
      <Point X="214.0" Y="195.0" T="1650653648"/>
      <Point X="211.892692050519" Y="195.0" T="1650653648"/>
      <Point X="210.0" Y="195.0" T="1650653648"/>
      <Point X="209.0992754395733" Y="195.0" T="1650653648"/>
      <Point X="207.0" Y="195.0" T="1650653648"/>
      <Point X="206.30585882862758" Y="195.0" T="1650653648"/>
      <Point X="205.0" Y="195.0" T="1650653648"/>
      <Point X="203.51244221768187" Y="195.0" T="1650653648"/>
      <Point X="202.0" Y="195.0" T="1650653648"/>
      <Point X="201.0" Y="195.0" T="1650653648"/>
      <Point X="201.0" Y="194.71902560673615" T="1650653648"/>
      <Point X="201.0" Y="194.0" T="1650653648"/>
      <Point X="201.0" Y="193.0" T="1650653648"/>
    </Stroke>
  </Gesture>
