<?xml version="1.0" ?>
  <Gesture Name="asterisk09" Subject="4" Speed="medium" Number="9" NumPts="230" AppName="dollarstore-notepad" Date="2022-04-19" Time="1650425451">
    <Stroke>
      <Point X="192.0" Y="304.0" T="1650425451"/>
      <Point X="192.0" Y="305.0" T="1650425451"/>
      <Point X="192.8402037013515" Y="305.8402037013515" T="1650425451"/>
      <Point X="194.38751418388955" Y="307.38751418388955" T="1650425451"/>
      <Point X="195.9348246664276" Y="308.9348246664276" T="1650425451"/>
      <Point X="197.48213514896565" Y="310.48213514896565" T="1650425451"/>
      <Point X="199.0294456315037" Y="312.0294456315037" T="1650425451"/>
      <Point X="200.57675611404173" Y="313.57675611404176" T="1650425451"/>
      <Point X="201.0" Y="314.0" T="1650425451"/>
      <Point X="202.0345436696514" Y="315.20696761459334" T="1650425451"/>
      <Point X="203.45862323003126" Y="316.86839376836986" T="1650425451"/>
      <Point X="204.88270279041112" Y="318.5298199221464" T="1650425451"/>
      <Point X="206.30678235079097" Y="320.1912460759229" T="1650425451"/>
      <Point X="207.73086191117082" Y="321.8526722296994" T="1650425451"/>
      <Point X="209.1549414715507" Y="323.51409838347587" T="1650425451"/>
      <Point X="210.57902103193055" Y="325.1755245372524" T="1650425451"/>
      <Point X="212.00310059231043" Y="326.83695069102885" T="1650425451"/>
      <Point X="213.0" Y="328.0" T="1650425451"/>
      <Point X="213.44787442836608" Y="328.4798654589637" T="1650425451"/>
      <Point X="214.9409419668183" Y="330.0795806787339" T="1650425451"/>
      <Point X="216.4340095052705" Y="331.67929589850417" T="1650425451"/>
      <Point X="217.9270770437227" Y="333.2790111182744" T="1650425451"/>
      <Point X="219.4201445821749" Y="334.87872633804466" T="1650425451"/>
      <Point X="220.91321212062712" Y="336.47844155781485" T="1650425451"/>
      <Point X="222.40627965907933" Y="338.0781567775851" T="1650425451"/>
      <Point X="223.89934719753157" Y="339.6778719973553" T="1650425451"/>
      <Point X="225.39241473598378" Y="341.27758721712553" T="1650425451"/>
      <Point X="226.88548227443601" Y="342.8773024368957" T="1650425451"/>
      <Point X="227.0" Y="343.0" T="1650425451"/>
      <Point X="228.5149658310688" Y="344.3367345568254" T="1650425451"/>
      <Point X="230.15578162393015" Y="345.7845131975854" T="1650425451"/>
      <Point X="231.7965974167915" Y="347.2322918383454" T="1650425451"/>
      <Point X="233.43741320965287" Y="348.68007047910544" T="1650425451"/>
      <Point X="235.07822900251423" Y="350.12784911986546" T="1650425451"/>
      <Point X="236.7190447953756" Y="351.5756277606255" T="1650425451"/>
      <Point X="238.35986058823696" Y="353.0234064013855" T="1650425451"/>
      <Point X="240.00067638109832" Y="354.4711850421455" T="1650425451"/>
      <Point X="241.64149217395968" Y="355.91896368290554" T="1650425451"/>
      <Point X="243.28230796682104" Y="357.3667423236656" T="1650425451"/>
      <Point X="244.0" Y="358.0" T="1650425451"/>
      <Point X="244.9980254422505" Y="358.7207961527365" T="1650425451"/>
      <Point X="246.77197599887523" Y="360.00198266585437" T="1650425451"/>
      <Point X="248.54592655549996" Y="361.28316917897223" T="1650425451"/>
      <Point X="250.3198771121247" Y="362.5643556920901" T="1650425451"/>
      <Point X="252.0938276687494" Y="363.84554220520795" T="1650425451"/>
      <Point X="253.86777822537414" Y="365.1267287183258" T="1650425451"/>
      <Point X="255.64172878199886" Y="366.40791523144367" T="1650425451"/>
      <Point X="257.4156793386236" Y="367.6891017445615" T="1650425451"/>
      <Point X="259.18962989524834" Y="368.9702882576794" T="1650425451"/>
      <Point X="260.9635804518731" Y="370.25147477079724" T="1650425451"/>
      <Point X="262.0" Y="371.0" T="1650425451"/>
      <Point X="262.74030966459094" Y="371.52879261756493" T="1650425451"/>
      <Point X="264.5209435992245" Y="372.800673999446" T="1650425451"/>
      <Point X="266.301577533858" Y="374.0725553813271" T="1650425451"/>
      <Point X="268.08221146849155" Y="375.3444367632082" T="1650425451"/>
      <Point X="269.86284540312505" Y="376.6163181450893" T="1650425451"/>
      <Point X="271.64347933775855" Y="377.88819952697037" T="1650425451"/>
      <Point X="273.42411327239205" Y="379.16008090885146" T="1650425451"/>
      <Point X="275.2047472070256" Y="380.43196229073254" T="1650425451"/>
      <Point X="276.0" Y="381.0" T="1650425451"/>
      <Point X="276.9956241314047" Y="381.68927824481864" T="1650425451"/>
      <Point X="278.79476767045634" Y="382.93483915646976" T="1650425451"/>
      <Point X="280.59391120950795" Y="384.1804000681209" T="1650425451"/>
      <Point X="282.39305474855956" Y="385.425960979772" T="1650425451"/>
      <Point X="284.1921982876112" Y="386.67152189142314" T="1650425451"/>
      <Point X="285.9913418266628" Y="387.91708280307427" T="1650425451"/>
      <Point X="287.7904853657144" Y="389.16264371472533" T="1650425451"/>
      <Point X="289.0" Y="390.0" T="1650425451"/>
      <Point X="289.5966985684695" Y="390.3977990456463" T="1650425451"/>
      <Point X="291.4174138786345" Y="391.61160925242297" T="1650425451"/>
      <Point X="293.23812918879946" Y="392.8254194591996" T="1650425451"/>
      <Point X="295.0" Y="394.0" T="1650425451"/>
      <Point X="295.0588444989644" Y="394.0392296659763" T="1650425451"/>
      <Point X="296.8795598091294" Y="395.25303987275294" T="1650425451"/>
      <Point X="298.0" Y="396.0" T="1650425451"/>
    </Stroke>
    <Stroke>
      <Point X="313.0" Y="291.0" T="1650425451"/>
      <Point X="312.0" Y="291.0" T="1650425451"/>
      <Point X="311.0" Y="291.0" T="1650425451"/>
      <Point X="310.9081461585081" Y="291.1049758188479" T="1650425451"/>
      <Point X="309.49928310127916" Y="292.71510502710953" T="1650425451"/>
      <Point X="308.09042004405023" Y="294.32523423537117" T="1650425451"/>
      <Point X="306.6815569868213" Y="295.9353634436328" T="1650425451"/>
      <Point X="305.2726939295924" Y="297.54549265189445" T="1650425451"/>
      <Point X="304.0" Y="299.0" T="1650425451"/>
      <Point X="303.8616678716653" Y="299.1537023648163" T="1650425451"/>
      <Point X="302.4304254996148" Y="300.7439716670946" T="1650425451"/>
      <Point X="300.99918312756427" Y="302.33424096937296" T="1650425451"/>
      <Point X="299.56794075551375" Y="303.9245102716513" T="1650425451"/>
      <Point X="298.1366983834632" Y="305.5147795739296" T="1650425451"/>
      <Point X="296.7054560114127" Y="307.10504887620795" T="1650425451"/>
      <Point X="295.2742136393622" Y="308.6953181784863" T="1650425451"/>
      <Point X="293.84297126731167" Y="310.28558748076466" T="1650425451"/>
      <Point X="292.41172889526115" Y="311.87585678304305" T="1650425451"/>
      <Point X="290.98048652321063" Y="313.46612608532143" T="1650425451"/>
      <Point X="289.5492441511601" Y="315.0563953875998" T="1650425451"/>
      <Point X="288.1180017791096" Y="316.6466646898782" T="1650425451"/>
      <Point X="286.68675940705907" Y="318.23693399215654" T="1650425451"/>
      <Point X="286.0" Y="319.0" T="1650425451"/>
      <Point X="285.31126439342296" Y="319.8741644237324" T="1650425451"/>
      <Point X="283.98719436143193" Y="321.55471484895173" T="1650425451"/>
      <Point X="282.6631243294409" Y="323.23526527417107" T="1650425451"/>
      <Point X="281.3390542974499" Y="324.9158156993904" T="1650425451"/>
      <Point X="280.01498426545885" Y="326.59636612460974" T="1650425451"/>
      <Point X="278.6909142334678" Y="328.2769165498291" T="1650425451"/>
      <Point X="277.3668442014768" Y="329.9574669750484" T="1650425451"/>
      <Point X="276.04277416948577" Y="331.6380174002678" T="1650425451"/>
      <Point X="274.71870413749474" Y="333.3185678254872" T="1650425451"/>
      <Point X="273.3946341055037" Y="334.9991182507066" T="1650425451"/>
      <Point X="272.0705640735127" Y="336.679668675926" T="1650425451"/>
      <Point X="270.74649404152166" Y="338.3602191011454" T="1650425451"/>
      <Point X="269.4224240095307" Y="340.0407695263648" T="1650425451"/>
      <Point X="268.09835397753966" Y="341.7213199515841" T="1650425451"/>
      <Point X="266.7742839455487" Y="343.4018703768035" T="1650425451"/>
      <Point X="265.45021391355766" Y="345.08242080202285" T="1650425451"/>
      <Point X="264.1261438815667" Y="346.76297122724225" T="1650425451"/>
      <Point X="262.80207384957566" Y="348.4435216524616" T="1650425451"/>
      <Point X="261.4780038175847" Y="350.124072077681" T="1650425451"/>
      <Point X="260.15393378559367" Y="351.8046225029003" T="1650425451"/>
      <Point X="260.0" Y="352.0" T="1650425451"/>
      <Point X="258.92883234730505" Y="353.5580620402835" T="1650425451"/>
      <Point X="257.716750427325" Y="355.3210902875272" T="1650425451"/>
      <Point X="256.50466850734495" Y="357.08411853477094" T="1650425451"/>
      <Point X="255.29258658736492" Y="358.84714678201465" T="1650425451"/>
      <Point X="254.0805046673849" Y="360.61017502925836" T="1650425451"/>
      <Point X="252.86842274740485" Y="362.37320327650207" T="1650425451"/>
      <Point X="251.6563408274248" Y="364.1362315237458" T="1650425451"/>
      <Point X="250.44425890744475" Y="365.8992597709895" T="1650425451"/>
      <Point X="249.2321769874647" Y="367.66228801823314" T="1650425451"/>
      <Point X="249.0" Y="368.0" T="1650425451"/>
      <Point X="247.96220115242681" Y="369.38373179676427" T="1650425451"/>
      <Point X="246.67850803283952" Y="371.0953226228807" T="1650425451"/>
      <Point X="245.3948149132522" Y="372.8069134489971" T="1650425451"/>
      <Point X="244.1111217936649" Y="374.5185042751135" T="1650425451"/>
      <Point X="243.0" Y="376.0" T="1650425451"/>
      <Point X="242.83083071710362" Y="376.2326077639825" T="1650425451"/>
      <Point X="241.57244411470123" Y="377.96288934228585" T="1650425451"/>
      <Point X="240.31405751229883" Y="379.6931709205891" T="1650425451"/>
      <Point X="239.05567090989643" Y="381.4234524988924" T="1650425451"/>
      <Point X="237.79728430749404" Y="383.15373407719574" T="1650425451"/>
      <Point X="236.5388977050916" Y="384.884015655499" T="1650425451"/>
      <Point X="235.28051110268922" Y="386.61429723380235" T="1650425451"/>
      <Point X="235.0" Y="387.0" T="1650425451"/>
      <Point X="233.82438682490738" Y="388.1756131750926" T="1650425451"/>
      <Point X="232.3115399752029" Y="389.6884600247971" T="1650425451"/>
      <Point X="231.0" Y="391.0" T="1650425451"/>
      <Point X="230.84208189518398" Y="391.236877157224" T="1650425451"/>
      <Point X="229.6553071863039" Y="393.0170392205441" T="1650425451"/>
      <Point X="229.0" Y="394.0" T="1650425451"/>
      <Point X="228.32250918288582" Y="394.6774908171142" T="1650425451"/>
      <Point X="228.0" Y="395.0" T="1650425451"/>
      <Point X="227.0" Y="395.0" T="1650425451"/>
      <Point X="226.3166083277815" Y="395.0" T="1650425451"/>
      <Point X="226.0" Y="395.0" T="1650425451"/>
      <Point X="225.0" Y="395.0" T="1650425451"/>
    </Stroke>
    <Stroke>
      <Point X="251.0" Y="296.0" T="1650425451"/>
      <Point X="251.0" Y="297.0" T="1650425451"/>
      <Point X="251.0" Y="298.21811223770163" T="1650425451"/>
      <Point X="251.0" Y="300.0" T="1650425451"/>
      <Point X="251.0" Y="300.43622447540326" T="1650425451"/>
      <Point X="251.0" Y="302.6543367131049" T="1650425451"/>
      <Point X="251.0" Y="304.87244895080653" T="1650425451"/>
      <Point X="251.0" Y="307.09056118850816" T="1650425451"/>
      <Point X="251.0" Y="309.3086734262098" T="1650425451"/>
      <Point X="251.0" Y="311.0" T="1650425451"/>
      <Point X="250.98746103781662" Y="311.52663641170165" T="1650425451"/>
      <Point X="250.93466380476266" Y="313.7441201999679" T="1650425451"/>
      <Point X="250.8818665717087" Y="315.9616039882341" T="1650425451"/>
      <Point X="250.82906933865476" Y="318.17908777650035" T="1650425451"/>
      <Point X="250.7762721056008" Y="320.3965715647666" T="1650425451"/>
      <Point X="250.72347487254686" Y="322.6140553530328" T="1650425451"/>
      <Point X="250.6706776394929" Y="324.83153914129906" T="1650425451"/>
      <Point X="250.61788040643896" Y="327.0490229295653" T="1650425451"/>
      <Point X="250.565083173385" Y="329.26650671783153" T="1650425451"/>
      <Point X="250.51228594033105" Y="331.48399050609777" T="1650425451"/>
      <Point X="250.4594887072771" Y="333.701474294364" T="1650425451"/>
      <Point X="250.40669147422315" Y="335.91895808263024" T="1650425451"/>
      <Point X="250.35389424116917" Y="338.1364418708965" T="1650425451"/>
      <Point X="250.30109700811522" Y="340.3539256591627" T="1650425451"/>
      <Point X="250.24829977506124" Y="342.57140944742895" T="1650425451"/>
      <Point X="250.1955025420073" Y="344.7888932356952" T="1650425451"/>
      <Point X="250.1427053089533" Y="347.0063770239614" T="1650425451"/>
      <Point X="250.08990807589936" Y="349.22386081222766" T="1650425451"/>
      <Point X="250.03711084284538" Y="351.4413446004939" T="1650425451"/>
      <Point X="250.0" Y="353.0" T="1650425451"/>
      <Point X="250.09319880993596" Y="353.6523916695518" T="1650425451"/>
      <Point X="250.4068872508783" Y="355.84821075614815" T="1650425451"/>
      <Point X="250.72057569182064" Y="358.0440298427445" T="1650425451"/>
      <Point X="251.0" Y="360.0" T="1650425451"/>
      <Point X="251.01343949858267" Y="360.2419109744882" T="1650425451"/>
      <Point X="251.13647822793294" Y="362.456608102793" T="1650425451"/>
      <Point X="251.2595169572832" Y="364.6713052310978" T="1650425451"/>
      <Point X="251.38255568663348" Y="366.8860023594026" T="1650425451"/>
      <Point X="251.50559441598375" Y="369.1006994877074" T="1650425451"/>
      <Point X="251.62863314533402" Y="371.3153966160122" T="1650425451"/>
      <Point X="251.7516718746843" Y="373.530093744317" T="1650425451"/>
      <Point X="251.87471060403456" Y="375.7447908726218" T="1650425451"/>
      <Point X="251.9977493333848" Y="377.9594880009266" T="1650425451"/>
      <Point X="252.0" Y="378.0" T="1650425451"/>
      <Point X="252.1448476577239" Y="380.17271486585844" T="1650425451"/>
      <Point X="252.29239428900647" Y="382.38591433509725" T="1650425451"/>
      <Point X="252.43994092028905" Y="384.59911380433607" T="1650425451"/>
      <Point X="252.58748755157163" Y="386.8123132735749" T="1650425451"/>
      <Point X="252.73503418285424" Y="389.0255127428137" T="1650425451"/>
      <Point X="252.88258081413682" Y="391.2387122120525" T="1650425451"/>
      <Point X="253.0" Y="393.0" T="1650425451"/>
      <Point X="253.03012744541942" Y="393.45191168129134" T="1650425451"/>
      <Point X="253.177674076702" Y="395.66511115053015" T="1650425451"/>
      <Point X="253.32522070798458" Y="397.87831061976897" T="1650425451"/>
      <Point X="253.47276733926716" Y="400.0915100890078" T="1650425451"/>
      <Point X="253.62031397054974" Y="402.3047095582466" T="1650425451"/>
      <Point X="253.76786060183235" Y="404.5179090274854" T="1650425451"/>
      <Point X="253.91540723311493" Y="406.73110849672423" T="1650425451"/>
      <Point X="254.0" Y="408.0" T="1650425451"/>
      <Point X="254.0941707278111" Y="408.94170727811104" T="1650425451"/>
      <Point X="254.31488114466842" Y="411.1488114466841" T="1650425451"/>
      <Point X="254.5355915615257" Y="413.3559156152571" T="1650425451"/>
      <Point X="254.75630197838302" Y="415.56301978383016" T="1650425451"/>
      <Point X="254.9770123952403" Y="417.7701239524032" T="1650425451"/>
      <Point X="255.0" Y="418.0" T="1650425451"/>
      <Point X="255.1650188150778" Y="419.9802257809334" T="1650425451"/>
      <Point X="255.34922301022718" Y="422.190676122726" T="1650425451"/>
      <Point X="255.53342720537657" Y="424.40112646451865" T="1650425451"/>
      <Point X="255.71763140052596" Y="426.6115768063113" T="1650425451"/>
      <Point X="255.90183559567532" Y="428.8220271481039" T="1650425451"/>
      <Point X="256.0" Y="430.0" T="1650425451"/>
      <Point X="256.11441327596236" Y="431.0297194836613" T="1650425451"/>
      <Point X="256.359362795377" Y="433.2342651583935" T="1650425451"/>
      <Point X="256.60431231479174" Y="435.4388108331257" T="1650425451"/>
      <Point X="256.8492618342064" Y="437.64335650785785" T="1650425451"/>
      <Point X="257.0" Y="439.0" T="1650425451"/>
    </Stroke>
  </Gesture>
